Workbook

Sheet 费用汇总
A1: 油气长输管道工程勘察测量费用测算表
A2: 项目名称：铜梁/江津-遵义-贵阳天然气管道勘察测量（标段一）
A3: 序号 | B3: 项目 | C3: 费用（万元） | D3: 备注
A4: 1 | B4: 长输管道线路工程勘察测量费用 | C4: ='表1-长输管道工程勘测费用'!I9/10000 -> 0 | D4: 测算明细见附表1
A5: 2 | B5: 通用工程测量费用 | C5: ='表2-通用工程测量费用'!N49/10000 -> 0 | D5: 测算明细见附表2
A6: 3 | B6: 地质测绘费用 | C6: ='表3-地质测绘'!R13/10000 -> 0 | D6: 测算明细见附表3
A7: 4 | B7: 通用工程勘察费用 | C7: ='表4-通用工程勘察费用'!R209/10000 -> 0 | D7: 测算明细见附表4
A8: 小计 | C8: =SUM(C4:C7) -> 0
C9: 0.9 | D9: 管网其他费用和相关费用计价依据
A10: 5 | B10: 浮动后勘察费 | C10: =C9*C8 -> 0
A11: 6 | B11: 其他相关费用 | C11: ='表5-其他费用'!R17/10000 -> 39.356 | D11: 测算明细见附表5
A12: 合计（含税） | C12: =ROUND(C10+C11,4) -> 39.356
A13: 合计（不含税） | C13: =ROUND(C12/1.06,4) -> 37.1283
A14: 增值税 | C14: =C12-C13 -> 2.2277

Sheet 表1-长输管道工程勘测费用
A1: 附表1油气长输管道线路工程勘察测量费用测算表
A2: 序号 | B2: 工作任务 | D2: 类别或级别 | E2: 费用（元） | J2: 收费标准里对应条款
B3: 名称 | C3: 划分 | E3: 单位 | F3: 基价（元） | G3: 数量 | H3: 附加调整系数 | I3: 小计
A4: 1 | C4: 初步勘察 | D4: Ⅱ | E4: km | F4: =IF(C4="初步勘察",VLOOKUP(D4,{"Ⅰ","2200";"Ⅱ","3300";"Ⅲ","5100";"Ⅳ","7700";"Ⅴ","11100"},2,0),VLOOKUP(D4,{"Ⅰ","7100";"Ⅱ","10800";"Ⅲ","16700";"Ⅳ","25200";"Ⅴ","36400"},2,0)) -> 3300 | H4: 1 | I4: =F4*G4*H4 -> 0 | J4: 表12.3-1
A5: 2 | C5: 详细勘察 | D5: Ⅲ | E5: km | F5: =IF(C5="初步勘察",VLOOKUP(D5,{"Ⅰ","2200";"Ⅱ","3300";"Ⅲ","5100";"Ⅳ","7700";"Ⅴ","11100"},2,0),VLOOKUP(D5,{"Ⅰ","7100";"Ⅱ","10800";"Ⅲ","16700";"Ⅳ","25200";"Ⅴ","36400"},2,0)) -> 16700 | H5: 2 | I5: =F5*G5*H5 -> 0 | J5: 表12.3-1
A9: 合计 | I9: =SUM(I4:I8) -> 0

Sheet 表2-通用工程测量费用
A1: 附表2油气长输管道通用工程测量费用测算表
A2: 序号 | B2: 工作任务 | H2: 工程勘察实物工作费（元） | L2: 工程勘察技术工作费（元） | N2: 金额合计（元） | O2: 收费标准里对应条款 | P2: 备注
B3: 项目 | C3: 内容 | D3: (空) | E3: 类别 | F3: 比例尺 | G3: 单位 | H3: 基价（元） | I3: 工程量合计 | J3: 实物工作费调整系数 | K3: 小计 | L3: 技术工作费调整系数 | M3: 小计 | Q3: 0 | R3: 预警参数 | S3: 预警细节 | T3: 【经验数】单价 | U3: 【DWB批注】价格or总体 | V3: 【经验数】实物工作费调整系数 | W3: 【DWB批注】-实物工作费调整系数 | X3: 【经验数】技术工作费调整系数 | Y3: 【DWB批注】-技术工作费调整系数 | Z3: 差值校验 | AF3: 匹配报告预留位置 | AL3: 委托方信息抓取
A4: 映射行 | B4: 要素1 | C4: 要素2 | D4: 要素3 | E4: 要素4 | F4: 要素5 | G4: 单位 | H4: 单价匹配-测试 | I4: 数量 | J4: 实物工作费调整系数-测试 | L4: 技术工作费调整系数-测试 | R4: 预警参数 | S4: 预警细节 | T4: (不要被管勘智算脚本识别) | U4: (不要被管勘智算脚本识别) | V4: (不要被管勘智算脚本识别) | W4: (不要被管勘智算脚本识别) | X4: (不要被管勘智算脚本识别) | Y4: (不要被管勘智算脚本识别) | Z4: 差值校验 | AA4: 差值校验 | AB4: 差值校验 | AC4: 单价111匹配-测试 | AD4: 实物111工作费调整系数-测试 | AE4: 技术111工作费调整系数-测试 | AF4: 匹配报告预留位置 | AG4: 匹配状态 | AH4: 候选数量 | AI4: 匹配说明 | AJ4: 匹配说明-实物工作费调整系数 | AK4: 匹配说明-技术工作费调整系数 | AL4: 数量(信息抓取) | AM4: 实物工作费调整系数(信息抓取) | AN4: 实物工作费调整系数(信息抓取) | AO4: 委托方备注(信息抓取) | AP4: 抓取日志
A5: 1 | B5: 控制测量 | C5: 首级控制测量 | E5: GPS测量C级 | F5: 中等 | G5: 个 | I5: 26 | K5: =I5*J5*H5 -> 0 | M5: =K5*L5 -> 0 | N5: =K5+M5 -> 0 | O5: 表2.2-2 | P5: 不造标系数0.6 | T5: =IF(E5="GPS测量E级",VLOOKUP(F5,{"简单","2821";"中等","3203";"复杂","4123"},2,0))+IF(E5="GPS测量D级",VLOOKUP(F5,{"简单","3198";"中等","3632";"复杂","4671"},2,0))+IF(E5="GPS测量C级",VLOOKUP(F5,{"简单","3727";"中等","4274";"复杂","5500"},2,0)) -> 4274 | U5: 来自2002《使用手册》表2.2-2，控制测量，GPS测量C级，中等复杂程度，4274元/点。 | V5: 0.6 | W5: 表2.2-3 | X5: 0.22 | Y5: 工程测量技术工作收费比例通常为`22%`。在《使用手册》第25页可以找到这一比例 | Z5: =H5+AC5-T5 -> -4274 | AA5: =J5+AD5-V5 -> -0.6 | AB5: =L5+AE5-X5 -> -0.22
A6: 2 | C6: 首级控制测量 | E6: GPS测量E级 | F6: 中等 | G6: 个 | I6: 62 | K6: =I6*J6*H6 -> 0 | M6: =K6*L6 -> 0 | N6: =K6+M6 -> 0 | P6: 不造标系数0.6 | T6: =IF(E6="GPS测量E级",VLOOKUP(F6,{"简单","2821";"中等","3203";"复杂","4123"},2,0))+IF(E6="GPS测量D级",VLOOKUP(F6,{"简单","3198";"中等","3632";"复杂","4671"},2,0))+IF(E6="GPS测量C级",VLOOKUP(F6,{"简单","3727";"中等","4274";"复杂","5500"},2,0)) -> 3203 | V6: 0.6 | W6: 【系数】元素1为"控制测量","二、三、四等三角(边)不造标"，系数0.6 | X6: 0.22 | Y6: 【第一层】【系数】【默认】除了特殊说明的，所有行默认系数0.22 | Z6: =H6+AC6-T6 -> -3203 | AA6: =J6+AD6-V6 -> -0.6 | AB6: =L6+AE6-X6 -> -0.22
A7: 3 | C7: 河流静态 | E7: GPS测量E级 | F7: 复杂 | G7: 点 | K7: =I7*J7*H7 -> 0 | M7: =K7*L7 -> 0 | N7: =K7+M7 -> 0 | T7: =IF(E7="GPS测量E级",VLOOKUP(F7,{"简单","2821";"中等","3203";"复杂","4123"},2,0))+IF(E7="GPS测量D级",VLOOKUP(F7,{"简单","3198";"中等","3632";"复杂","4671"},2,0))+IF(E7="GPS测量C级",VLOOKUP(F7,{"简单","3727";"中等","4274";"复杂","5500"},2,0)) -> 4123 | V7: 0.6 | X7: 0.22 | Z7: =H7+AC7-T7 -> -4123 | AA7: =J7+AD7-V7 -> -0.6 | AB7: =L7+AE7-X7 -> -0.22
A8: 4 | C8: 连片鱼塘静态 | E8: GPS测量E级 | F8: 复杂 | G8: 点 | K8: =I8*J8*H8 -> 0 | M8: =K8*L8 -> 0 | N8: =K8+M8 -> 0 | T8: =IF(E8="GPS测量E级",VLOOKUP(F8,{"简单","2821";"中等","3203";"复杂","4123"},2,0))+IF(E8="GPS测量D级",VLOOKUP(F8,{"简单","3198";"中等","3632";"复杂","4671"},2,0))+IF(E8="GPS测量C级",VLOOKUP(F8,{"简单","3727";"中等","4274";"复杂","5500"},2,0)) -> 4123 | V8: 0.6 | X8: 0.22 | Z8: =H8+AC8-T8 -> -4123 | AA8: =J8+AD8-V8 -> -0.6 | AB8: =L8+AE8-X8 -> -0.22
A9: 5 | C9: 山岭隧道静态 | E9: GPS测量E级 | F9: 复杂 | G9: 点 | K9: =I9*J9*H9 -> 0 | M9: =K9*L9 -> 0 | N9: =K9+M9 -> 0 | T9: =IF(E9="GPS测量E级",VLOOKUP(F9,{"简单","2821";"中等","3203";"复杂","4123"},2,0))+IF(E9="GPS测量D级",VLOOKUP(F9,{"简单","3198";"中等","3632";"复杂","4671"},2,0))+IF(E9="GPS测量C级",VLOOKUP(F9,{"简单","3727";"中等","4274";"复杂","5500"},2,0)) -> 4123 | V9: 0.6 | X9: 0.22 | Z9: =H9+AC9-T9 -> -4123 | AA9: =J9+AD9-V9 -> -0.6 | AB9: =L9+AE9-X9 -> -0.22
A10: 6 | C10: 山体定向钻静态 | E10: GPS测量E级 | F10: 复杂 | G10: 点 | K10: =I10*J10*H10 -> 0 | M10: =K10*L10 -> 0 | N10: =K10+M10 -> 0 | T10: =IF(E10="GPS测量E级",VLOOKUP(F10,{"简单","2821";"中等","3203";"复杂","4123"},2,0))+IF(E10="GPS测量D级",VLOOKUP(F10,{"简单","3198";"中等","3632";"复杂","4671"},2,0))+IF(E10="GPS测量C级",VLOOKUP(F10,{"简单","3727";"中等","4274";"复杂","5500"},2,0)) -> 4123 | V10: 0.6 | X10: 0.22 | Z10: =H10+AC10-T10 -> -4123 | AA10: =J10+AD10-V10 -> -0.6 | AB10: =L10+AE10-X10 -> -0.22
A11: 7 | C11: 站场静态 | E11: GPS测量E级 | F11: 中等 | G11: 点 | K11: =I11*J11*H11 -> 0 | M11: =K11*L11 -> 0 | N11: =K11+M11 -> 0 | T11: =IF(E11="GPS测量E级",VLOOKUP(F11,{"简单","2821";"中等","3203";"复杂","4123"},2,0))+IF(E11="GPS测量D级",VLOOKUP(F11,{"简单","3198";"中等","3632";"复杂","4671"},2,0))+IF(E11="GPS测量C级",VLOOKUP(F11,{"简单","3727";"中等","4274";"复杂","5500"},2,0)) -> 3203 | V11: 0.6 | X11: 0.22 | Z11: =H11+AC11-T11 -> -3203 | AA11: =J11+AD11-V11 -> -0.6 | AB11: =L11+AE11-X11 -> -0.22
A12: 8 | C12: 阀室RTK | E12: 三角（边）一级 | F12: 中等 | G12: 点 | K12: =I12*J12*H12 -> 0 | M12: =K12*L12 -> 0 | N12: =K12+M12 -> 0 | T12: =IF(E12="GPS测量E级",VLOOKUP(F12,{"简单","2821";"中等","3203";"复杂","4123"},2,0))+IF(E12="GPS测量D级",VLOOKUP(F12,{"简单","3198";"中等","3632";"复杂","4671"},2,0))+IF(E12="GPS测量C级",VLOOKUP(F12,{"简单","3727";"中等","4274";"复杂","5500"},2,0))+IF(E12="三角（边）一级",VLOOKUP(F12,{"简单","1096";"中等","1244";"复杂","1602"},2,0)) -> 1244 | V12: 0.6 | W12: 注意：没有直接写“三角（边）一级不造标0.6”，应作为样表经验规则 | X12: 0.22 | Z12: =H12+AC12-T12 -> -1244 | AA12: =J12+AD12-V12 -> -0.6 | AB12: =L12+AE12-X12 -> -0.22
A13: 9 | C13: 渣场RTK | E13: 三角（边）一级 | F13: 复杂 | G13: 点 | K13: =I13*J13*H13 -> 0 | M13: =K13*L13 -> 0 | N13: =K13+M13 -> 0 | T13: =IF(E13="GPS测量E级",VLOOKUP(F13,{"简单","2821";"中等","3203";"复杂","4123"},2,0))+IF(E13="GPS测量D级",VLOOKUP(F13,{"简单","3198";"中等","3632";"复杂","4671"},2,0))+IF(E13="GPS测量C级",VLOOKUP(F13,{"简单","3727";"中等","4274";"复杂","5500"},2,0))+IF(E13="三角（边）一级",VLOOKUP(F13,{"简单","1096";"中等","1244";"复杂","1602"},2,0)) -> 1602 | V13: 0.6 | W13: 注意：没有直接写“三角（边）一级不造标0.6”，应作为样表经验规则 | X13: 0.22 | Z13: =H13+AC13-T13 -> -1602 | AA13: =J13+AD13-V13 -> -0.6 | AB13: =L13+AE13-X13 -> -0.22
A14: 10 | C14: 公路、铁路RTK | E14: GPS测量E级 | F14: 复杂 | G14: 点 | K14: =I14*J14*H14 -> 0 | M14: =K14*L14 -> 0 | N14: =K14+M14 -> 0 | T14: =IF(E14="GPS测量E级",VLOOKUP(F14,{"简单","2821";"中等","3203";"复杂","4123"},2,0))+IF(E14="GPS测量D级",VLOOKUP(F14,{"简单","3198";"中等","3632";"复杂","4671"},2,0))+IF(E14="GPS测量C级",VLOOKUP(F14,{"简单","3727";"中等","4274";"复杂","5500"},2,0)) -> 4123 | V14: 0.6 | X14: 0.22 | Z14: =H14+AC14-T14 -> -4123 | AA14: =J14+AD14-V14 -> -0.6 | AB14: =L14+AE14-X14 -> -0.22
A15: 11 | C15: 小型穿越RTK | E15: GPS测量E级 | F15: 复杂 | G15: 点 | K15: =I15*J15*H15 -> 0 | M15: =K15*L15 -> 0 | N15: =K15+M15 -> 0 | T15: =IF(E15="GPS测量E级",VLOOKUP(F15,{"简单","2821";"中等","3203";"复杂","4123"},2,0))+IF(E15="GPS测量D级",VLOOKUP(F15,{"简单","3198";"中等","3632";"复杂","4671"},2,0))+IF(E15="GPS测量C级",VLOOKUP(F15,{"简单","3727";"中等","4274";"复杂","5500"},2,0)) -> 4123 | V15: 0.6 | X15: 0.22 | Z15: =H15+AC15-T15 -> -4123 | AA15: =J15+AD15-V15 -> -0.6 | AB15: =L15+AE15-X15 -> -0.22
A16: 12 | B16: 线路航测 | C16: 数据采集 | F16: 1:2000 | G16: km | K16: =I16*J16*H16 -> 0 | M16: / | N16: =K16 -> 0 | O16: （09标准）摄影测量与遥感 | P16: 行业市场价3500-5500 | T16: 4000 | U16: 《财建〔2009〕17号》测绘生产成本定额。 行业市场价3500-5500 | V16: 1 | X16: 0 | Y16: 【第一层】【系数】元素1为“线路航测”，系数0 | Z16: =H16+AC16-T16 -> -4000 | AA16: =J16+AD16-V16 -> -1 | AB16: =L16+AE16-X16 -> 0
A17: 13 | C17: 像控点联测 | E17: Ⅲ类 | F17: 1:2000 | G17: 幅 | K17: =I17*J17*H17 -> 0 | M17: / | N17: =K17 -> 0 | P17: 航线网布点核减15% | T17: =VLOOKUP(E17,{"Ⅰ类","2720.45";"Ⅱ类","3874.53";"Ⅲ类","4991.14"},2,0) -> 4991.14 | U17: 《财建〔2009〕17号》P14-像控点联测 | V17: 0.85 | W17: 航线网布点时定额核减15%。 区域网布点时定额核减30%。 | X17: 0 | Y17: 这些行在工作簿中没有再次叠加`22%`技术费。 | Z17: =H17+AC17-T17 -> -4991.14 | AA17: =J17+AD17-V17 -> -0.85 | AB17: =L17+AE17-X17 -> 0
A18: 14 | C18: 地物、地貌调绘 | E18: Ⅱ类 | F18: 1:2000 | G18: 幅 | K18: =I18*J18*H18 -> 0 | M18: / | N18: =K18 -> 0 | P18: 室内外综合判调，定额核减30% | T18: =VLOOKUP(E18,{"Ⅰ类","2923.06";"Ⅱ类","5546.41";"Ⅲ类","7840.47"},2,0) -> 5546.41 | U18: 《财建〔2009〕17号》P15-地物、地貌调绘 | V18: 0.7 | W18: 系数0.7综合判调,不宜直接扩大适用 | X18: 0 | Z18: =H18+AC18-T18 -> -5546.41 | AA18: =J18+AD18-V18 -> -0.7 | AB18: =L18+AE18-X18 -> 0
A19: 15 | C19: DLG | E19: Ⅱ类 | F19: 1:2000 | G19: 幅 | K19: =I19*J19*H19 -> 0 | M19: / | N19: =K19 -> 0 | P19: 室内外综合判调，定额增加20%，带宽系数15% | T19: =VLOOKUP(E19,{"Ⅰ类","6487.94";"Ⅱ类","9039.5";"Ⅲ类","12750.88"},2,0) -> 9039.5 | V19: 1.35 | W19: 系数1.2综合判调,不宜直接扩大适用 | X19: 0 | Z19: =H19+AC19-T19 -> -9039.5 | AA19: =J19+AD19-V19 -> -1.35 | AB19: =L19+AE19-X19 -> 0
A20: 16 | C20: DEM | E20: Ⅱ类 | F20: 1:2000 | G20: 幅 | K20: =I20*J20*H20 -> 0 | M20: / | N20: =K20 -> 0 | T20: =VLOOKUP(E20,{"Ⅰ类","1570.81";"Ⅱ类","2290.69";"Ⅲ类","3010.6"},2,0) -> 2290.69 | V20: 1 | X20: 0 | Z20: =H20+AC20-T20 -> -2290.69 | AA20: =J20+AD20-V20 -> -1 | AB20: =L20+AE20-X20 -> 0
A21: 17 | C21: DOM | E21: Ⅱ类 | F21: 1:2000 | G21: 幅 | K21: =I21*J21*H21 -> 0 | M21: / | N21: =K21 -> 0 | T21: =VLOOKUP(E21,{"Ⅰ类","1437.18";"Ⅱ类","1727.65";"Ⅲ类","2018.11"},2,0) -> 1727.65 | V21: 1 | X21: 0 | Z21: =H21+AC21-T21 -> -1727.65 | AA21: =J21+AD21-V21 -> -1 | AB21: =L21+AE21-X21 -> 0
A22: 18 | B22: 走向图编制 | C22: 地图编制 | E22: Ⅱ类 | F22: 1:50000 | G22: 幅 | I22: 2 | K22: =I22*J22*H22 -> 0 | M22: / | N22: =K22 -> 0 | O22: （09标准）地图编制-P19 | T22: =IF(F22="1:50000",VLOOKUP(E22,{"Ⅰ类","3645.35";"Ⅱ类","4983.36";"Ⅲ类","7533.19"},2,0),VLOOKUP(E22,{"Ⅰ类","1991.38";"Ⅱ类","2742.11";"Ⅲ类","3517.45"},2,0)) -> 4983.36 | U22: 《财建〔2009〕17号》测绘生产成本定额。P19 | V22: 1 | X22: 0 | Y22: 【第一层】【系数】元素1为“走向图编制”，系数0 | Z22: =H22+AC22-T22 -> -4983.36 | AA22: =J22+AD22-V22 -> -1 | AB22: =L22+AE22-X22 -> 0
A23: 19 | B23: 地形图测绘（地形测量） | C23: 山岭隧道（洞身） | E23: 中等 | F23: 1:2000 | G23: km2 | K23: =I23*J23*H23 -> 0 | M23: =K23*L23 -> 0 | N23: =K23+M23 -> 0 | O23: 表2.2-2 | P23: 数字化测绘系数1.5、植被覆盖系数1.3 | T23: =VLOOKUP(E23,{"简单","6676";"中等","8901";"复杂","14244"},2,0) -> 8901 | U23: 2002表2.2-2 | V23: 1.8 | X23: 0.22 | Z23: =H23+AC23-T23 -> -8901 | AA23: =J23+AD23-V23 -> -1.8 | AB23: =L23+AE23-X23 -> -0.22
A24: 20 | C24: 山岭隧道（洞身） | E24: 复杂 | F24: 1:2000 | G24: km2 | I24: 2.704 | K24: =I24*J24*H24 -> 0 | M24: =K24*L24 -> 0 | N24: =K24+M24 -> 0 | P24: 数字化测绘系数1.5、植被覆盖系数1.3 | T24: =VLOOKUP(E24,{"简单","6676";"中等","8901";"复杂","14244"},2,0) -> 14244 | V24: 1.8 | W24: 【系数】数字化测绘，系数1.5 | X24: 0.22 | Z24: =H24+AC24-T24 -> -14244 | AA24: =J24+AD24-V24 -> -1.8 | AB24: =L24+AE24-X24 -> -0.22
A25: 21 | C25: 山岭隧道（洞口、渣场） | E25: 中等 | F25: 1:500 | G25: km2 | K25: =I25*J25*H25 -> 0 | M25: =K25*L25 -> 0 | N25: =K25+M25 -> 0 | P25: 数字化测绘系数1.5、植被覆盖系数1.3 | T25: =VLOOKUP(E25,{"简单","33383";"中等","44510";"复杂","71216"},2,0) -> 44510 | V25: 1.8 | W25: 【系数】植被覆盖，系数1.3 （其实套用的是“覆盖或隐蔽程度>60%，1.2-1.5”） | X25: 0.22 | Z25: =H25+AC25-T25 -> -44510 | AA25: =J25+AD25-V25 -> -1.8 | AB25: =L25+AE25-X25 -> -0.22
A26: 22 | C26: 山岭隧道（洞口、渣场） | E26: 复杂 | F26: 1:500 | G26: km2 | I26: 0.4 | K26: =I26*J26*H26 -> 0 | M26: =K26*L26 -> 0 | N26: =K26+M26 -> 0 | P26: 数字化测绘系数1.5、植被覆盖系数1.3 | T26: =VLOOKUP(E26,{"简单","33383";"中等","44510";"复杂","71216"},2,0) -> 71216 | V26: 1.8 | X26: 0.22 | Z26: =H26+AC26-T26 -> -71216 | AA26: =J26+AD26-V26 -> -1.8 | AB26: =L26+AE26-X26 -> -0.22
A27: 23 | C27: 河流大中型穿越（陆地） | E27: 复杂 | F27: 1:1000 | G27: km2 | I27: 0.632 | K27: =I27*J27*H27 -> 0 | M27: =K27*L27 -> 0 | N27: =K27+M27 -> 0 | P27: 数字化测绘系数1.5 | T27: =VLOOKUP(E27,{"简单","15174";"中等","20232";"复杂","32374"},2,0) -> 32374 | V27: 1.5 | X27: 0.22 | Z27: =H27+AC27-T27 -> -32374 | AA27: =J27+AD27-V27 -> -1.5 | AB27: =L27+AE27-X27 -> -0.22
A28: 24 | C28: 河流大中型穿越（水域） | E28: 复杂 | F28: 1:1000 | G28: km2 | I28: 0.28 | K28: =I28*J28*H28 -> 0 | M28: =K28*L28 -> 0 | N28: =K28+M28 -> 0 | O28: 表2.3-1 | P28: 数字化测绘系数1.5 | T28: =VLOOKUP(E28,{"简单","40464";"中等","53817";"复杂","75680"},2,0) -> 75680 | V28: 1.5 | X28: 0.22 | Z28: =H28+AC28-T28 -> -75680 | AA28: =J28+AD28-V28 -> -1.5 | AB28: =L28+AE28-X28 -> -0.22
A29: 25 | C29: 连片鱼塘穿越 | E29: 复杂 | F29: 1:1000 | G29: km2 | K29: =I29*J29*H29 -> 0 | M29: =K29*L29 -> 0 | N29: =K29+M29 -> 0 | O29: 表2.2-2 | P29: 数字化测绘系数1.5 | T29: =VLOOKUP(E29,{"简单","15174";"中等","20232";"复杂","32374"},2,0) -> 32374 | V29: 1.5 | X29: 0.22 | Z29: =H29+AC29-T29 -> -32374 | AA29: =J29+AD29-V29 -> -1.5 | AB29: =L29+AE29-X29 -> -0.22
A30: 26 | C30: 山体定向钻 | E30: 复杂 | F30: 1:1000 | G30: km2 | K30: =I30*J30*H30 -> 0 | M30: =K30*L30 -> 0 | N30: =K30+M30 -> 0 | P30: 数字化测绘系数1.5、植被覆盖系数1.3 | T30: =VLOOKUP(E30,{"简单","15174";"中等","20232";"复杂","32374"},2,0) -> 32374 | V30: 1.8 | W30: 【经验数】数字化测绘系数1.5、植被覆盖系数1.3 | X30: 0.22 | Z30: =H30+AC30-T30 -> -32374 | AA30: =J30+AD30-V30 -> -1.8 | AB30: =L30+AE30-X30 -> -0.22
A31: 27 | C31: 站场（地形图） | E31: 复杂 | F31: 1:500 | G31: km2 | I31: 0.5 | K31: =I31*J31*H31 -> 0 | M31: =K31*L31 -> 0 | N31: =K31+M31 -> 0 | P31: 数字化测绘系数1.5 | T31: =VLOOKUP(E31,{"简单","33383";"中等","44510";"复杂","71216"},2,0) -> 71216 | V31: 1.5 | X31: 0.22 | Z31: =H31+AC31-T31 -> -71216 | AA31: =J31+AD31-V31 -> -1.5 | AB31: =L31+AE31-X31 -> -0.22
A32: 28 | C32: 站场（地形图） | E32: 中等 | F32: 1:500 | G32: km2 | K32: =I32*J32*H32 -> 0 | M32: =K32*L32 -> 0 | N32: =K32+M32 -> 0 | P32: 数字化测绘系数1.5 | T32: =VLOOKUP(E32,{"简单","33383";"中等","44510";"复杂","71216"},2,0) -> 44510 | V32: 1.5 | X32: 0.22 | Z32: =H32+AC32-T32 -> -44510 | AA32: =J32+AD32-V32 -> -1.5 | AB32: =L32+AE32-X32 -> -0.22
A33: 29 | C33: 站场（区位图） | E33: 复杂 | F33: 1:2000 | G33: km2 | I33: 2 | K33: =I33*J33*H33 -> 0 | M33: =K33*L33 -> 0 | N33: =K33+M33 -> 0 | P33: 数字化测绘系数1.5 | T33: =VLOOKUP(E33,{"简单","6676";"中等","8901";"复杂","14244"},2,0) -> 14244 | V33: 1.5 | X33: 0.22 | Z33: =H33+AC33-T33 -> -14244 | AA33: =J33+AD33-V33 -> -1.5 | AB33: =L33+AE33-X33 -> -0.22
A34: 30 | C34: 站场（区位图） | E34: 中等 | F34: 1:2000 | G34: km2 | K34: =I34*J34*H34 -> 0 | M34: =K34*L34 -> 0 | N34: =K34+M34 -> 0 | P34: 数字化测绘系数1.5 | T34: =VLOOKUP(E34,{"简单","6676";"中等","8901";"复杂","14244"},2,0) -> 8901 | V34: 1.5 | X34: 0.22 | Z34: =H34+AC34-T34 -> -8901 | AA34: =J34+AD34-V34 -> -1.5 | AB34: =L34+AE34-X34 -> -0.22
A35: 31 | C35: 阀室（地形图） | E35: 复杂 | F35: 1:500 | G35: km2 | I35: 0.72 | K35: =I35*J35*H35 -> 0 | M35: =K35*L35 -> 0 | N35: =K35+M35 -> 0 | P35: 数字化测绘系数1.5 | T35: =VLOOKUP(E35,{"简单","33383";"中等","44510";"复杂","71216"},2,0) -> 71216 | V35: 1.5 | X35: 0.22 | Z35: =H35+AC35-T35 -> -71216 | AA35: =J35+AD35-V35 -> -1.5 | AB35: =L35+AE35-X35 -> -0.22
A36: 32 | C36: 阀室 | E36: 中等 | F36: 1:500 | G36: km2 | K36: =I36*J36*H36 -> 0 | M36: =K36*L36 -> 0 | N36: =K36+M36 -> 0 | P36: 数字化测绘系数1.5 | T36: =VLOOKUP(E36,{"简单","33383";"中等","44510";"复杂","71216"},2,0) -> 44510 | V36: 1.5 | X36: 0.22 | Z36: =H36+AC36-T36 -> -44510 | AA36: =J36+AD36-V36 -> -1.5 | AB36: =L36+AE36-X36 -> -0.22
A37: 33 | C37: 公路、铁路、小型穿越 | E37: 中等 | F37: 1:500 | G37: km2 | K37: =I37*J37*H37 -> 0 | M37: =K37*L37 -> 0 | N37: =K37+M37 -> 0 | P37: 数字化测绘系数1.5 | T37: =VLOOKUP(E37,{"简单","33383";"中等","44510";"复杂","71216"},2,0) -> 44510 | V37: 1.5 | X37: 0.22 | Z37: =H37+AC37-T37 -> -44510 | AA37: =J37+AD37-V37 -> -1.5 | AB37: =L37+AE37-X37 -> -0.22
A38: 34 | B38: 断面测量 | C38: 线路纵断面 | E38: 中等 | F38: 1:2000 | G38: km | K38: =I38*J38*H38 -> 0 | M38: =K38*L38 -> 0 | N38: =K38+M38 -> 0 | P38: 数字化测绘系数1.5 | T38: =VLOOKUP(E38,{"简单","468";"中等","625";"复杂","860"},2,0) -> 625 | V38: 1.5 | X38: 0.22 | Z38: =H38+AC38-T38 -> -625 | AA38: =J38+AD38-V38 -> -1.5 | AB38: =L38+AE38-X38 -> -0.22
A39: 35 | C39: 山岭隧道（洞身） | E39: 复杂 | F39: 1:2000 | G39: km | I39: 7.16 | K39: =I39*J39*H39 -> 0 | M39: =K39*L39 -> 0 | N39: =K39+M39 -> 0 | P39: 植被覆盖系数1.3 | T39: =VLOOKUP(E39,{"简单","468";"中等","625";"复杂","860"},2,0) -> 860 | V39: 1.3 | X39: 0.22 | Z39: =H39+AC39-T39 -> -860 | AA39: =J39+AD39-V39 -> -1.3 | AB39: =L39+AE39-X39 -> -0.22
A40: 36 | C40: 山岭隧道（洞口） | E40: 复杂 | F40: 1:500 | G40: km | I40: 2.8 | K40: =I40*J40*H40 -> 0 | M40: =K40*L40 -> 0 | N40: =K40+M40 -> 0 | P40: 植被覆盖系数1.3 | T40: =VLOOKUP(E40,{"简单","785";"中等","1047";"复杂","1440"},2,0) -> 1440 | V40: 1.3 | X40: 0.22 | Z40: =H40+AC40-T40 -> -1440 | AA40: =J40+AD40-V40 -> -1.3 | AB40: =L40+AE40-X40 -> -0.22
A41: 37 | C41: 河流大中型穿越（陆地） | E41: 中等 | F41: 1:1000 | G41: km | I41: 1.58 | K41: =I41*J41*H41 -> 0 | M41: =K41*L41 -> 0 | N41: =K41+M41 -> 0 | T41: =VLOOKUP(E41,{"简单","607";"中等","809";"复杂","1113"},2,0) -> 809 | V41: 1 | X41: 0.22 | Z41: =H41+AC41-T41 -> -809 | AA41: =J41+AD41-V41 -> -1 | AB41: =L41+AE41-X41 -> -0.22
A42: 38 | C42: 河流大中型穿越（水域） | E42: 中等 | F42: 1:1000 | G42: km | I42: 0.7 | K42: =I42*J42*H42 -> 0 | M42: =K42*L42 -> 0 | N42: =K42+M42 -> 0 | O42: 表2.3-1 | T42: =VLOOKUP(E42,{"简单","2023";"中等","2698";"复杂","4046"},2,0) -> 2698 | V42: 1 | X42: 0.22 | Z42: =H42+AC42-T42 -> -2698 | AA42: =J42+AD42-V42 -> -1 | AB42: =L42+AE42-X42 -> -0.22
A43: 39 | C43: 连片鱼塘穿越 | E43: 中等 | F43: 1:1000 | G43: km | K43: =I43*J43*H43 -> 0 | M43: =K43*L43 -> 0 | N43: =K43+M43 -> 0 | O43: 表2.2-2 | P43: 数字化测绘系数1.5 | T43: =VLOOKUP(E43,{"简单","607";"中等","809";"复杂","1113"},2,0) -> 809 | V43: 1.5 | X43: 0.22 | Z43: =H43+AC43-T43 -> -809 | AA43: =J43+AD43-V43 -> -1.5 | AB43: =L43+AE43-X43 -> -0.22
A44: 40 | C44: 山体定向钻 | E44: 复杂 | F44: 1:1000 | G44: km | K44: =I44*J44*H44 -> 0 | M44: =K44*L44 -> 0 | N44: =K44+M44 -> 0 | P44: 数字化测绘系数1.5 | T44: =VLOOKUP(E44,{"简单","607";"中等","809";"复杂","1113"},2,0) -> 1113 | V44: 1.5 | X44: 0.22 | Z44: =H44+AC44-T44 -> -1113 | AA44: =J44+AD44-V44 -> -1.5 | AB44: =L44+AE44-X44 -> -0.22
A45: 41 | C45: 公路、铁路、小型穿越 | E45: 中等 | F45: 1:500 | G45: km | K45: =I45*J45*H45 -> 0 | M45: =K45*L45 -> 0 | N45: =K45+M45 -> 0 | P45: 数字化测绘系数1.5 | T45: =VLOOKUP(E45,{"简单","785";"中等","1047";"复杂","1440"},2,0) -> 1047 | V45: 1.5 | X45: 0.22 | Z45: =H45+AC45-T45 -> -1047 | AA45: =J45+AD45-V45 -> -1.5 | AB45: =L45+AE45-X45 -> -0.22
A46: 42 | B46: 地下管线测量 | C46: 地下管线测量 | E46: 中等 | F46: / | G46: km | I46: 8 | K46: =I46*J46*H46 -> 0 | M46: =K46*L46 -> 0 | N46: =K46+M46 -> 0 | O46: 表2.4-1 | T46: =VLOOKUP(E46,{"简单","1416";"中等","1700";"复杂","2337"},2,0) -> 1700 | V46: 1 | X46: 0.22 | Z46: =H46+AC46-T46 -> -1700 | AA46: =J46+AD46-V46 -> -1 | AB46: =L46+AE46-X46 -> -0.22
A47: 43 | C47: 盲探管线 | E47: 中等 | G47: m2 | K47: =I47*J47*H47 -> 0 | M47: =K47*L47 -> 0 | N47: =K47+M47 -> 0 | O47: 表7.2-1 | P47: 地下管线探测部分，（预估工作量） | T47: =VLOOKUP(E47,{"简单","1";"中等","1.5";"复杂","2"},2,0) -> 1.5 | V47: 1 | W47: 地下管线探测部分，（预估工作量） | X47: 0.22 | Z47: =H47+AC47-T47 -> -1.5 | AA47: =J47+AD47-V47 -> -1 | AB47: =L47+AE47-X47 -> -0.22
A48: 44 | C48: 金属管线探查 | E48: 中等 | F48: / | G48: km | I48: 8 | K48: =I48*J48*H48 -> 0 | M48: =K48*L48 -> 0 | N48: =K48+M48 -> 0 | O48: 表7.2-1 | T48: =VLOOKUP(E48,{"简单","2250";"中等","4500";"复杂","7200"},2,0) -> 4500 | V48: 1 | X48: 0.22 | Z48: =H48+AC48-T48 -> -4500 | AA48: =J48+AD48-V48 -> -1 | AB48: =L48+AE48-X48 -> -0.22
A49: 合计 | B49: 合计 | K49: =SUM(K5:K48) -> 0 | M49: =SUM(M5:M48) -> 0 | N49: =SUM(N5:N48) -> 0 | Z49: =H49+AC49-T49 -> 0 | AA49: =J49+AD49-V49 -> 0 | AB49: =L49+AE49-X49 -> 0
W50: 【】【问题】怎么判断数字化或者植被覆盖？
V52: 【实物工作费附加调整系数】 | X52: 【技术工作费附加调整系数】
V53: 数字化测绘系数1.5 | X53: 线路航测、走向图编制 不加系数
V54: 植被覆盖系数0.3
V59: 默认;1.0 | X59: 默认;0.22

Sheet 表3-地质测绘
A1: 附表3油气长输管道通用工程地质测绘费用测算表
A2: ID | B2: 工作任务 | H2: 实物工作费（元） | O2: 技术工作费（元） | R2: 金额合计 | S2: 收费标准里对应条款 | T2: 备注
B3: 项目 | D3: 内容 | E3: 类别 | F3: 级别 | G3: 单位 | H3: 基价（元） | I3: 工程量合计 | J3: 空 | K3: 空 | L3: 取费系数说明 | M3: 实物工作费调整系数 | N3: 小计 | O3: 类别 | P3: 技术工作费调整系数 | Q3: 小计 | R3: （元） | U3: 0 | V3: 预警信息 | W3: 预警细节 | X3: 【经验数】单价 | Y3: 【DWB批注】价格or总体 | Z3: 【经验数】实物工作费调整系数 | AA3: 【DWB批注】-实物工作费调整系数 | AB3: 【经验数】技术工作费调整系数 | AC3: 【DWB批注】-技术工作费调整系数 | AD3: 差值校验 | AJ3: 匹配报告预留位置 | AP3: 委托方信息抓取
A4: 映射行 | B4: 要素1 | C4: 要素2 | D4: 要素3 | E4: 要素4 | F4: 要素5 | G4: 单位 | H4: 单价匹配-测试 | I4: 数量 | M4: 实物工作费调整系数-测试 | O4: 要素-技术 | P4: 技术工作费调整系数-测试 | V4: 预警参数 | W4: 预警细节 | X4: (不要被管勘智算脚本识别) | Y4: (不要被管勘智算脚本识别) | Z4: (不要被管勘智算脚本识别) | AA4: (不要被管勘智算脚本识别) | AB4: (不要被管勘智算脚本识别) | AC4: (不要被管勘智算脚本识别) | AD4: 差值校验 | AE4: 差值校验 | AF4: 差值校验 | AG4: 单价111匹配-测试 | AH4: 实物111工作费调整系数-测试 | AI4: 技术111工作费调整系数-测试 | AJ4: 匹配报告预留位置 | AK4: 匹配状态 | AL4: 候选数量 | AM4: 匹配说明 | AN4: 匹配说明-实物工作费调整系数 | AO4: 匹配说明-技术工作费调整系数 | AP4: 数量(信息抓取) | AQ4: 实物工作费调整系数(信息抓取) | AR4: 实物工作费调整系数(信息抓取) | AS4: 委托方备注(信息抓取) | AT4: 抓取日志
A5: 1 | B5: 岩土工程勘察 | C5: 地质测绘 | D5: 成图比例 | E5: 1:500 | F5: 中等 | G5: km2 | N5: =H5*I5*M5 -> 0 | O5: 甲级 | Q5: =N5*P5 -> 0 | R5: =N5+Q5 -> 0 | S5: 表3.2-1、表3.2-2 | X5: =VLOOKUP($F5,{"简单","8033";"中等","11475";"复杂","17213"},2,0) -> 11475 | Y5: 《使用手册》第39—40页是地质测绘收费基价和附加调整规则。 | Z5: 1 | AB5: =VLOOKUP($O5,{"甲级","1.2";"乙级","1.0";"丙级","0.8"},2,0) -> 1.2 | AC5: 【第一层】【系数】要素1：岩土工程勘察。 系数："甲级","1.2";"乙级","1.0";"丙级","0.8"} | AD5: =H5+AG5-X5 -> -11475 | AE5: =M5+AH5-Z5 -> -1 | AF5: =P5+AI5-AB5 -> -1.2
A6: 2 | E6: 1:1000 | F6: 中等 | G6: km2 | I6: 0.5 | N6: =H6*I6*M6 -> 0 | O6: 甲级 | Q6: =N6*P6 -> 0 | R6: =N6+Q6 -> 0 | S6: 表3.2-1、表3.2-2 | X6: =VLOOKUP($F6,{"简单","5355";"中等","7650";"复杂","11475"},2,0) -> 7650 | Y6: 为啥表3-地质测绘单独一个表 | Z6: 1 | AB6: =VLOOKUP($O6,{"甲级","1.2";"乙级","1.0";"丙级","0.8"},2,0) -> 1.2 | AD6: =H6+AG6-X6 -> -7650 | AE6: =M6+AH6-Z6 -> -1 | AF6: =P6+AI6-AB6 -> -1.2
A7: 3 | E7: 1:1000 | F7: 复杂 | G7: km2 | N7: =H7*I7*M7 -> 0 | O7: 甲级 | Q7: =N7*P7 -> 0 | R7: =N7+Q7 -> 0 | S7: 表3.2-1、表3.2-2 | X7: =VLOOKUP($F7,{"简单","5355";"中等","7650";"复杂","11475"},2,0) -> 11475 | Z7: 1 | AB7: =VLOOKUP($O7,{"甲级","1.2";"乙级","1.0";"丙级","0.8"},2,0) -> 1.2 | AD7: =H7+AG7-X7 -> -11475 | AE7: =M7+AH7-Z7 -> -1 | AF7: =P7+AI7-AB7 -> -1.2
A8: 4 | E8: 1:2000 | F8: 中等 | G8: km2 | I8: 3.776 | N8: =H8*I8*M8 -> 0 | O8: 甲级 | Q8: =N8*P8 -> 0 | R8: =N8+Q8 -> 0 | S8: 表3.2-1、表3.2-2 | X8: =VLOOKUP($F8,{"简单","3570";"中等","5100";"复杂","7650"},2,0) -> 5100 | Z8: 1 | AB8: =VLOOKUP($O8,{"甲级","1.2";"乙级","1.0";"丙级","0.8"},2,0) -> 1.2 | AD8: =H8+AG8-X8 -> -5100 | AE8: =M8+AH8-Z8 -> -1 | AF8: =P8+AI8-AB8 -> -1.2
A9: 5 | E9: 1:10000 | F9: 复杂 | G9: km2 | N9: =H9*I9*M9 -> 0 | O9: 甲级 | Q9: =N9*P9 -> 0 | R9: =N9+Q9 -> 0 | T9: 带状工程地质测绘系数1.3 | X9: =VLOOKUP($F9,{"简单","536";"中等","765";"复杂","1148"},2,0) -> 1148 | Z9: 1.3 | AA9: 带状工程地质测绘系数1.3 | AB9: =VLOOKUP($O9,{"甲级","1.2";"乙级","1.0";"丙级","0.8"},2,0) -> 1.2 | AD9: =H9+AG9-X9 -> -1148 | AE9: =M9+AH9-Z9 -> -1.3 | AF9: =P9+AI9-AB9 -> -1.2
A10: 6 | E10: 1:10000 | F10: 中等 | G10: km2 | N10: =H10*I10*M10 -> 0 | O10: 甲级 | Q10: =N10*P10 -> 0 | R10: =N10+Q10 -> 0 | T10: 带状工程地质测绘系数1.3 | X10: =VLOOKUP($F10,{"简单","536";"中等","765";"复杂","1148"},2,0) -> 765 | Z10: 1.3 | AA10: 带状工程地质测绘系数1.3 | AB10: =VLOOKUP($O10,{"甲级","1.2";"乙级","1.0";"丙级","0.8"},2,0) -> 1.2 | AD10: =H10+AG10-X10 -> -765 | AE10: =M10+AH10-Z10 -> -1.3 | AF10: =P10+AI10-AB10 -> -1.2
A11: 7 | E11: 1:50000 | F11: 复杂 | G11: km2 | I11: 17.34 | N11: =H11*I11*M11 -> 0 | O11: 甲级 | Q11: =N11*P11 -> 0 | R11: =N11+Q11 -> 0 | S11: 表3.2-1、表3.2-2 | T11: 带状工程地质测绘系数1.3 | X11: =VLOOKUP($F11,{"简单","134";"中等","191";"复杂","287"},2,0) -> 287 | Z11: 1.3 | AA11: 带状工程地质测绘系数1.3 | AB11: =VLOOKUP($O11,{"甲级","1.2";"乙级","1.0";"丙级","0.8"},2,0) -> 1.2 | AD11: =H11+AG11-X11 -> -287 | AE11: =M11+AH11-Z11 -> -1.3 | AF11: =P11+AI11-AB11 -> -1.2
A12: 8 | E12: 1:50000 | F12: 中等 | G12: km2 | I12: 192.92 | N12: =H12*I12*M12 -> 0 | O12: 甲级 | Q12: =N12*P12 -> 0 | R12: =N12+Q12 -> 0 | S12: 表3.2-1、表3.2-2 | T12: 带状工程地质测绘系数1.3 | X12: =VLOOKUP($F12,{"简单","134";"中等","191";"复杂","287"},2,0) -> 191 | Z12: 1.3 | AA12: 带状工程地质测绘系数1.3 | AB12: =VLOOKUP($O12,{"甲级","1.2";"乙级","1.0";"丙级","0.8"},2,0) -> 1.2 | AD12: =H12+AG12-X12 -> -191 | AE12: =M12+AH12-Z12 -> -1.3 | AF12: =P12+AI12-AB12 -> -1.2
A13: 合计 | B13: 合计 | N13: =SUM(N5:N12) -> 0 | Q13: =SUM(Q5:Q12) -> 0 | R13: =SUM(R5:R12) -> 0 | AD13: =H13+AG13-X13 -> 0 | AE13: =M13+AH13-Z13 -> 0 | AF13: =P13+AI13-AB13 -> 0
Z15: 【实物工作费附加调整系数】 | AB15: 【技术工作费附加调整系数】
Z16: 带状工程地质测绘系数:1.3 | AB16: 默认;1.2
Z17: 与其他测绘工作同时进行:1.5 | AB17: 此列规则明确，不需要经验数
Z18: 默认;1.0

Sheet 表4-通用工程勘察费用
A1: 附表4油气长输管道通用工程勘察费用测算表
A2: 序号 | B2: 工作任务 | H2: 实物工作费（元） | O2: 技术工作费（元） | R2: 金额合计 | S2: 收费标准里对应条款 | T2: 收费标准里对应条款
B3: 项目 | D3: 内容 | E3: 类别 | F3: 级别 | G3: 单位 | H3: 基价（元） | I3: 工程量合计 | J3: 空 | K3: 空 | L3: 取费系数说明 | M3: 实物工作费调整系数 | N3: 小计 | O3: 类别 | P3: 技术工作费调整系数 | Q3: 小计 | R3: （元） | U3: 0 | V3: 预警参数 | W3: 预警细节 | X3: 【经验数】单价 | Y3: 【DWB批注】价格or总体 | Z3: 【经验数】实物工作费调整系数 | AA3: 【DWB批注】-实物工作费调整系数 | AB3: 【经验数】技术工作费调整系数 | AC3: 【DWB批注】-技术工作费调整系数 | AD3: 差值校验 | AJ3: 匹配报告预留位置 | AP3: 委托方信息抓取
A4: 映射行 | B4: 要素1 | C4: 要素2 | D4: 要素3 | E4: 要素4 | F4: 要素5 | G4: 单位 | H4: 单价匹配-测试 | I4: 数量 | M4: 实物工作费调整系数-测试 | O4: 要素-技术 | P4: 技术工作费调整系数-测试 | V4: 预警参数 | W4: 预警细节 | X4: (不要被管勘智算脚本识别) | Y4: (不要被管勘智算脚本识别) | Z4: (不要被管勘智算脚本识别) | AA4: (不要被管勘智算脚本识别) | AB4: (不要被管勘智算脚本识别) | AC4: (不要被管勘智算脚本识别) | AD4: 差值校验 | AE4: 差值校验 | AF4: 差值校验 | AG4: 单价111匹配-测试 | AH4: 实物111工作费调整系数-测试 | AI4: 技术111工作费调整系数-测试 | AJ4: 匹配报告预留位置 | AK4: 匹配状态 | AL4: 候选数量 | AM4: 匹配说明 | AN4: 匹配说明-实物工作费调整系数 | AO4: 匹配说明-技术工作费调整系数 | AP4: 数量(信息抓取) | AQ4: 实物工作费调整系数(信息抓取) | AR4: 实物工作费调整系数(信息抓取) | AS4: 委托方备注(信息抓取) | AT4: 抓取日志
A5: 1 | B5: 勘探点测放 | G5: 组日 | I5: 10 | N5: =H5*I5*M5 -> 0 | O5: 甲级 | Q5: =N5*P5 -> 0 | R5: =N5+Q5 -> 0 | X5: 1000 | Z5: 1 | AC5: 【第一层】【系数】要素1：勘探点测放。 系数：经验数为0 | AD5: =H5+AG5-X5 -> -1000 | AE5: =M5+AH5-Z5 -> -1 | AF5: =P5+AI5-AB5 -> 0
A6: 2 | B6: 岩土工程勘察 | C6: 钻探 | D6: 陆上 | E6: D≤10 | F6: Ⅲ | G6: m | I6: 49 | N6: =H6*I6*M6 -> 0 | O6: 甲级 | Q6: =N6*P6 -> 0 | R6: =N6+Q6 -> 0 | S6: 表3.3-2、表3.3-5 | T6: 泥浆护壁系数1.5 | X6: =VLOOKUP(F6,{"Ⅰ","46";"Ⅱ","71";"Ⅲ","117";"Ⅳ","207";"Ⅴ","301";"Ⅵ","382"},2,0) -> 117 | Z6: 1.5 | AA6: 泥浆护壁系数1.5 | AB6: =VLOOKUP(O6,{"甲级","1.2";"乙级","1.0";"丙级","0.8"},2,0) -> 1.2 | AC6: 【第一层】【系数】要素1：岩土工程勘察。 系数："甲级","1.2";"乙级","1.0";"丙级","0.8" | AD6: =H6+AG6-X6 -> -117 | AE6: =M6+AH6-Z6 -> -1.5 | AF6: =P6+AI6-AB6 -> -1.2
A7: 3 | E7: D≤10 | F7: Ⅳ | G7: m | I7: 121 | N7: =H7*I7*M7 -> 0 | O7: 甲级 | Q7: =N7*P7 -> 0 | R7: =N7+Q7 -> 0 | S7: 表3.3-2、表3.3-5 | X7: =VLOOKUP(F7,{"Ⅰ","46";"Ⅱ","71";"Ⅲ","117";"Ⅳ","207";"Ⅴ","301";"Ⅵ","382"},2,0) -> 207 | Y7: 钻探基价可以在《使用手册》第42页附近的钻探收费表中找到。【表3.3-2】 | Z7: 1.5 | AB7: =VLOOKUP(O7,{"甲级","1.2";"乙级","1.0";"丙级","0.8"},2,0) -> 1.2 | AD7: =H7+AG7-X7 -> -207 | AE7: =M7+AH7-Z7 -> -1.5 | AF7: =P7+AI7-AB7 -> -1.2
A8: 4 | E8: D≤10 | F8: Ⅵ | G8: m | N8: =H8*I8*M8 -> 0 | O8: 甲级 | Q8: =N8*P8 -> 0 | R8: =N8+Q8 -> 0 | S8: 表3.3-2、表3.3-5 | X8: =VLOOKUP(F8,{"Ⅰ","46";"Ⅱ","71";"Ⅲ","117";"Ⅳ","207";"Ⅴ","301";"Ⅵ","382"},2,0) -> 382 | Y8: 泥浆护壁附加系数可以在第48—49页附近的附加调整系数表中找到。【表3.3-5】 | Z8: 1.5 | AB8: =VLOOKUP(O8,{"甲级","1.2";"乙级","1.0";"丙级","0.8"},2,0) -> 1.2 | AD8: =H8+AG8-X8 -> -382 | AE8: =M8+AH8-Z8 -> -1.5 | AF8: =P8+AI8-AB8 -> -1.2
A9: 5 | E9: 10＜D≤20 | F9: Ⅲ | G9: m | N9: =H9*I9*M9 -> 0 | O9: 甲级 | Q9: =N9*P9 -> 0 | R9: =N9+Q9 -> 0 | S9: 表3.3-2、表3.3-5 | X9: =VLOOKUP(F9,{"Ⅰ","58";"Ⅱ","89";"Ⅲ","147";"Ⅳ","259";"Ⅴ","377";"Ⅵ","477"},2,0) -> 147 | Z9: 1.5 | AB9: =VLOOKUP(O9,{"甲级","1.2";"乙级","1.0";"丙级","0.8"},2,0) -> 1.2 | AD9: =H9+AG9-X9 -> -147 | AE9: =M9+AH9-Z9 -> -1.5 | AF9: =P9+AI9-AB9 -> -1.2
A10: 6 | E10: 10＜D≤20 | F10: Ⅳ | G10: m | N10: =H10*I10*M10 -> 0 | O10: 甲级 | Q10: =N10*P10 -> 0 | R10: =N10+Q10 -> 0 | S10: 表3.3-2、表3.3-5 | X10: =VLOOKUP(F10,{"Ⅰ","58";"Ⅱ","89";"Ⅲ","147";"Ⅳ","259";"Ⅴ","377";"Ⅵ","477"},2,0) -> 259 | Z10: 1.5 | AB10: =VLOOKUP(O10,{"甲级","1.2";"乙级","1.0";"丙级","0.8"},2,0) -> 1.2 | AD10: =H10+AG10-X10 -> -259 | AE10: =M10+AH10-Z10 -> -1.5 | AF10: =P10+AI10-AB10 -> -1.2
A11: 7 | E11: 10＜D≤20 | F11: Ⅴ | G11: m | I11: 50 | N11: =H11*I11*M11 -> 0 | O11: 甲级 | Q11: =N11*P11 -> 0 | R11: =N11+Q11 -> 0 | S11: 表3.3-2、表3.3-5 | X11: =VLOOKUP(F11,{"Ⅰ","58";"Ⅱ","89";"Ⅲ","147";"Ⅳ","259";"Ⅴ","377";"Ⅵ","477"},2,0) -> 377 | Z11: 1.5 | AB11: =VLOOKUP(O11,{"甲级","1.2";"乙级","1.0";"丙级","0.8"},2,0) -> 1.2 | AD11: =H11+AG11-X11 -> -377 | AE11: =M11+AH11-Z11 -> -1.5 | AF11: =P11+AI11-AB11 -> -1.2
A12: 8 | E12: 20＜D≤30 | F12: Ⅳ | G12: m | I12: 30 | N12: =H12*I12*M12 -> 0 | O12: 甲级 | Q12: =N12*P12 -> 0 | R12: =N12+Q12 -> 0 | S12: 表3.3-2、表3.3-5 | X12: =VLOOKUP(F12,{"Ⅰ","69";"Ⅱ","107";"Ⅲ","176";"Ⅳ","311";"Ⅴ","452";"Ⅵ","573"},2,0) -> 311 | Z12: 1.5 | AB12: =VLOOKUP(O12,{"甲级","1.2";"乙级","1.0";"丙级","0.8"},2,0) -> 1.2 | AD12: =H12+AG12-X12 -> -311 | AE12: =M12+AH12-Z12 -> -1.5 | AF12: =P12+AI12-AB12 -> -1.2
A13: 9 | E13: 20＜D≤30 | F13: Ⅴ | G13: m | I13: 100 | N13: =H13*I13*M13 -> 0 | O13: 甲级 | Q13: =N13*P13 -> 0 | R13: =N13+Q13 -> 0 | S13: 表3.3-2、表3.3-5 | X13: =VLOOKUP(F13,{"Ⅰ","69";"Ⅱ","107";"Ⅲ","176";"Ⅳ","311";"Ⅴ","452";"Ⅵ","573"},2,0) -> 452 | Z13: 1.5 | AB13: =VLOOKUP(O13,{"甲级","1.2";"乙级","1.0";"丙级","0.8"},2,0) -> 1.2 | AD13: =H13+AG13-X13 -> -452 | AE13: =M13+AH13-Z13 -> -1.5 | AF13: =P13+AI13-AB13 -> -1.2
A14: 10 | E14: 20＜D≤30 | F14: Ⅵ | G14: m | I14: 40 | N14: =H14*I14*M14 -> 0 | O14: 甲级 | Q14: =N14*P14 -> 0 | R14: =N14+Q14 -> 0 | S14: 表3.3-2、表3.3-5 | X14: =VLOOKUP(F14,{"Ⅰ","69";"Ⅱ","107";"Ⅲ","176";"Ⅳ","311";"Ⅴ","452";"Ⅵ","573"},2,0) -> 573 | Z14: 1.5 | AB14: =VLOOKUP(O14,{"甲级","1.2";"乙级","1.0";"丙级","0.8"},2,0) -> 1.2 | AD14: =H14+AG14-X14 -> -573 | AE14: =M14+AH14-Z14 -> -1.5 | AF14: =P14+AI14-AB14 -> -1.2
A15: 11 | E15: 30＜D≤40 | F15: Ⅴ | G15: m | I15: 130 | N15: =H15*I15*M15 -> 0 | O15: 甲级 | Q15: =N15*P15 -> 0 | R15: =N15+Q15 -> 0 | S15: 表3.3-2、表3.3-5 | X15: =VLOOKUP(F15,{"Ⅰ","82";"Ⅱ","127";"Ⅲ","209";"Ⅳ","368";"Ⅴ","536";"Ⅵ","680"},2,0) -> 536 | Z15: 1.5 | AB15: =VLOOKUP(O15,{"甲级","1.2";"乙级","1.0";"丙级","0.8"},2,0) -> 1.2 | AD15: =H15+AG15-X15 -> -536 | AE15: =M15+AH15-Z15 -> -1.5 | AF15: =P15+AI15-AB15 -> -1.2
A16: 12 | E16: 30＜D≤40 | F16: Ⅵ | G16: m | I16: 40 | N16: =H16*I16*M16 -> 0 | O16: 甲级 | Q16: =N16*P16 -> 0 | R16: =N16+Q16 -> 0 | S16: 表3.3-2、表3.3-5 | X16: =VLOOKUP(F16,{"Ⅰ","82";"Ⅱ","127";"Ⅲ","209";"Ⅳ","368";"Ⅴ","536";"Ⅵ","680"},2,0) -> 680 | Z16: 1.5 | AB16: =VLOOKUP(O16,{"甲级","1.2";"乙级","1.0";"丙级","0.8"},2,0) -> 1.2 | AD16: =H16+AG16-X16 -> -680 | AE16: =M16+AH16-Z16 -> -1.5 | AF16: =P16+AI16-AB16 -> -1.2
A17: 13 | E17: 40＜D≤50 | F17: Ⅴ | G17: m | I17: 90 | N17: =H17*I17*M17 -> 0 | O17: 甲级 | Q17: =N17*P17 -> 0 | R17: =N17+Q17 -> 0 | S17: 表3.3-2、表3.3-5 | X17: =VLOOKUP(F17,{"Ⅰ","98";"Ⅱ","151";"Ⅲ","249";"Ⅳ","439";"Ⅴ","639";"Ⅵ","809"},2,0) -> 639 | Z17: 1.5 | AB17: =VLOOKUP(O17,{"甲级","1.2";"乙级","1.0";"丙级","0.8"},2,0) -> 1.2 | AD17: =H17+AG17-X17 -> -639 | AE17: =M17+AH17-Z17 -> -1.5 | AF17: =P17+AI17-AB17 -> -1.2
A18: 14 | E18: 40＜D≤50 | F18: Ⅵ | G18: m | I18: 80 | N18: =H18*I18*M18 -> 0 | O18: 甲级 | Q18: =N18*P18 -> 0 | R18: =N18+Q18 -> 0 | S18: 表3.3-2、表3.3-5 | X18: =VLOOKUP(F18,{"Ⅰ","98";"Ⅱ","151";"Ⅲ","249";"Ⅳ","439";"Ⅴ","639";"Ⅵ","809"},2,0) -> 809 | Z18: 1.5 | AB18: =VLOOKUP(O18,{"甲级","1.2";"乙级","1.0";"丙级","0.8"},2,0) -> 1.2 | AD18: =H18+AG18-X18 -> -809 | AE18: =M18+AH18-Z18 -> -1.5 | AF18: =P18+AI18-AB18 -> -1.2
A19: 15 | E19: 50＜D≤60 | F19: Ⅴ | G19: m | I19: 70 | N19: =H19*I19*M19 -> 0 | O19: 甲级 | Q19: =N19*P19 -> 0 | R19: =N19+Q19 -> 0 | S19: 表3.3-2、表3.3-5 | X19: =VLOOKUP(F19,{"Ⅰ","109";"Ⅱ","168";"Ⅲ","277";"Ⅳ","489";"Ⅴ","711";"Ⅵ","901"},2,0) -> 711 | Z19: 1.5 | AB19: =VLOOKUP(O19,{"甲级","1.2";"乙级","1.0";"丙级","0.8"},2,0) -> 1.2 | AD19: =H19+AG19-X19 -> -711 | AE19: =M19+AH19-Z19 -> -1.5 | AF19: =P19+AI19-AB19 -> -1.2
A20: 16 | E20: 50＜D≤60 | F20: Ⅵ | G20: m | I20: 40 | N20: =H20*I20*M20 -> 0 | O20: 甲级 | Q20: =N20*P20 -> 0 | R20: =N20+Q20 -> 0 | S20: 表3.3-2、表3.3-5 | X20: =VLOOKUP(F20,{"Ⅰ","109";"Ⅱ","168";"Ⅲ","277";"Ⅳ","489";"Ⅴ","711";"Ⅵ","901"},2,0) -> 901 | Z20: 1.5 | AB20: =VLOOKUP(O20,{"甲级","1.2";"乙级","1.0";"丙级","0.8"},2,0) -> 1.2 | AD20: =H20+AG20-X20 -> -901 | AE20: =M20+AH20-Z20 -> -1.5 | AF20: =P20+AI20-AB20 -> -1.2
A21: 17 | E21: 60＜D≤80 | F21: Ⅴ | G21: m | I21: 10 | N21: =H21*I21*M21 -> 0 | O21: 甲级 | Q21: =N21*P21 -> 0 | R21: =N21+Q21 -> 0 | S21: 表3.3-2、表3.3-5 | X21: =VLOOKUP(F21,{"Ⅰ","121";"Ⅱ","187";"Ⅲ","307";"Ⅳ","542";"Ⅴ","789";"Ⅵ","1000"},2,0) -> 789 | Z21: 1.5 | AB21: =VLOOKUP(O21,{"甲级","1.2";"乙级","1.0";"丙级","0.8"},2,0) -> 1.2 | AD21: =H21+AG21-X21 -> -789 | AE21: =M21+AH21-Z21 -> -1.5 | AF21: =P21+AI21-AB21 -> -1.2
A22: 18 | E22: 60＜D≤80 | F22: Ⅵ | G22: m | I22: 180 | N22: =H22*I22*M22 -> 0 | O22: 甲级 | Q22: =N22*P22 -> 0 | R22: =N22+Q22 -> 0 | S22: 表3.3-2、表3.3-5 | X22: =VLOOKUP(F22,{"Ⅰ","121";"Ⅱ","187";"Ⅲ","307";"Ⅳ","542";"Ⅴ","789";"Ⅵ","1000"},2,0) -> 1000 | Z22: 1.5 | AB22: =VLOOKUP(O22,{"甲级","1.2";"乙级","1.0";"丙级","0.8"},2,0) -> 1.2 | AD22: =H22+AG22-X22 -> -1000 | AE22: =M22+AH22-Z22 -> -1.5 | AF22: =P22+AI22-AB22 -> -1.2
A23: 19 | E23: 80＜D≤100 | F23: Ⅵ | G23: m | I23: 95 | N23: =H23*I23*M23 -> 0 | O23: 甲级 | Q23: =N23*P23 -> 0 | R23: =N23+Q23 -> 0 | S23: 表3.3-2、表3.3-5 | X23: =VLOOKUP(F23,{"Ⅰ","132";"Ⅱ","204";"Ⅲ","335";"Ⅳ","592";"Ⅴ","862";"Ⅵ","1092"},2,0) -> 1092 | Z23: 1.5 | AB23: =VLOOKUP(O23,{"甲级","1.2";"乙级","1.0";"丙级","0.8"},2,0) -> 1.2 | AD23: =H23+AG23-X23 -> -1092 | AE23: =M23+AH23-Z23 -> -1.5 | AF23: =P23+AI23-AB23 -> -1.2
A24: 20 | E24: 100＜D≤120 | F24: Ⅵ | G24: m | I24: 80 | N24: =H24*I24*M24 -> 0 | O24: 甲级 | Q24: =N24*P24 -> 0 | R24: =N24+Q24 -> 0 | S24: 表3.3-2、表3.3-5 | X24: 1310.4 | Z24: 1.5 | AB24: =VLOOKUP(O24,{"甲级","1.2";"乙级","1.0";"丙级","0.8"},2,0) -> 1.2 | AD24: =H24+AG24-X24 -> -1310.4 | AE24: =M24+AH24-Z24 -> -1.5 | AF24: =P24+AI24-AB24 -> -1.2
A25: 21 | E25: 120＜D≤140 | F25: Ⅵ | G25: m | I25: 80 | N25: =H25*I25*M25 -> 0 | O25: 甲级 | Q25: =N25*P25 -> 0 | R25: =N25+Q25 -> 0 | S25: 表3.3-2、表3.3-5 | X25: 1572.48 | Z25: 1.5 | AB25: =VLOOKUP(O25,{"甲级","1.2";"乙级","1.0";"丙级","0.8"},2,0) -> 1.2 | AD25: =H25+AG25-X25 -> -1572.48 | AE25: =M25+AH25-Z25 -> -1.5 | AF25: =P25+AI25-AB25 -> -1.2
A26: 22 | E26: 140＜D≤160 | F26: Ⅵ | G26: m | I26: 80 | N26: =H26*I26*M26 -> 0 | O26: 甲级 | Q26: =N26*P26 -> 0 | R26: =N26+Q26 -> 0 | S26: 表3.3-2、表3.3-5 | X26: 1886.976 | Z26: 1.5 | AB26: =VLOOKUP(O26,{"甲级","1.2";"乙级","1.0";"丙级","0.8"},2,0) -> 1.2 | AD26: =H26+AG26-X26 -> -1886.976 | AE26: =M26+AH26-Z26 -> -1.5 | AF26: =P26+AI26-AB26 -> -1.2
A27: 23 | E27: 160＜D≤180 | F27: Ⅵ | G27: m | I27: 80 | N27: =H27*I27*M27 -> 0 | O27: 甲级 | Q27: =N27*P27 -> 0 | R27: =N27+Q27 -> 0 | S27: 表3.3-2、表3.3-5 | X27: 2264.3712 | Z27: 1.5 | AB27: =VLOOKUP(O27,{"甲级","1.2";"乙级","1.0";"丙级","0.8"},2,0) -> 1.2 | AD27: =H27+AG27-X27 -> -2264.3712 | AE27: =M27+AH27-Z27 -> -1.5 | AF27: =P27+AI27-AB27 -> -1.2
A28: 24 | E28: 180＜D≤200 | F28: Ⅵ | G28: m | I28: 70 | N28: =H28*I28*M28 -> 0 | O28: 甲级 | Q28: =N28*P28 -> 0 | R28: =N28+Q28 -> 0 | S28: 表3.3-2、表3.3-5 | X28: 2717.2454 | Z28: 1.5 | AB28: =VLOOKUP(O28,{"甲级","1.2";"乙级","1.0";"丙级","0.8"},2,0) -> 1.2 | AD28: =H28+AG28-X28 -> -2717.2454 | AE28: =M28+AH28-Z28 -> -1.5 | AF28: =P28+AI28-AB28 -> -1.2
A29: 25 | E29: 200＜D≤220 | F29: Ⅵ | G29: m | I29: 60 | N29: =H29*I29*M29 -> 0 | O29: 甲级 | Q29: =N29*P29 -> 0 | R29: =N29+Q29 -> 0 | S29: 表3.3-2、表3.3-5 | X29: 3260.6945 | Z29: 1.5 | AB29: =VLOOKUP(O29,{"甲级","1.2";"乙级","1.0";"丙级","0.8"},2,0) -> 1.2 | AD29: =H29+AG29-X29 -> -3260.6945 | AE29: =M29+AH29-Z29 -> -1.5 | AF29: =P29+AI29-AB29 -> -1.2
A30: 26 | E30: 220＜D≤240 | F30: Ⅵ | G30: m | I30: 60 | N30: =H30*I30*M30 -> 0 | O30: 甲级 | Q30: =N30*P30 -> 0 | R30: =N30+Q30 -> 0 | S30: 表3.3-2、表3.3-5 | X30: 3912.8334 | Z30: 1.5 | AB30: =VLOOKUP(O30,{"甲级","1.2";"乙级","1.0";"丙级","0.8"},2,0) -> 1.2 | AD30: =H30+AG30-X30 -> -3912.8334 | AE30: =M30+AH30-Z30 -> -1.5 | AF30: =P30+AI30-AB30 -> -1.2
A31: 27 | E31: 240＜D≤260 | F31: Ⅵ | G31: m | I31: 60 | N31: =H31*I31*M31 -> 0 | O31: 甲级 | Q31: =N31*P31 -> 0 | R31: =N31+Q31 -> 0 | S31: 表3.3-2、表3.3-5 | X31: 4695.4001 | Z31: 1.5 | AB31: =VLOOKUP(O31,{"甲级","1.2";"乙级","1.0";"丙级","0.8"},2,0) -> 1.2 | AD31: =H31+AG31-X31 -> -4695.4001 | AE31: =M31+AH31-Z31 -> -1.5 | AF31: =P31+AI31-AB31 -> -1.2
A32: 28 | E32: 260＜D≤280 | F32: Ⅵ | G32: m | I32: 60 | N32: =H32*I32*M32 -> 0 | O32: 甲级 | Q32: =N32*P32 -> 0 | R32: =N32+Q32 -> 0 | S32: 表3.3-2、表3.3-5 | X32: 5634.4801 | Z32: 1.5 | AB32: =VLOOKUP(O32,{"甲级","1.2";"乙级","1.0";"丙级","0.8"},2,0) -> 1.2 | AD32: =H32+AG32-X32 -> -5634.4801 | AE32: =M32+AH32-Z32 -> -1.5 | AF32: =P32+AI32-AB32 -> -1.2
A33: 29 | E33: 280＜D≤300 | F33: Ⅵ | G33: m | I33: 60 | N33: =H33*I33*M33 -> 0 | O33: 甲级 | Q33: =N33*P33 -> 0 | R33: =N33+Q33 -> 0 | S33: 表3.3-2、表3.3-5 | X33: 6761.3762 | Z33: 1.5 | AB33: =VLOOKUP(O33,{"甲级","1.2";"乙级","1.0";"丙级","0.8"},2,0) -> 1.2 | AD33: =H33+AG33-X33 -> -6761.3762 | AE33: =M33+AH33-Z33 -> -1.5 | AF33: =P33+AI33-AB33 -> -1.2
A34: 30 | E34: 300＜D≤320 | F34: Ⅵ | G34: m | I34: 40 | N34: =H34*I34*M34 -> 0 | O34: 甲级 | Q34: =N34*P34 -> 0 | R34: =N34+Q34 -> 0 | S34: 表3.3-2、表3.3-5 | X34: 6761.3762 | Z34: 1.5 | AB34: =VLOOKUP(O34,{"甲级","1.2";"乙级","1.0";"丙级","0.8"},2,0) -> 1.2 | AD34: =H34+AG34-X34 -> -6761.3762 | AE34: =M34+AH34-Z34 -> -1.5 | AF34: =P34+AI34-AB34 -> -1.2
A35: 31 | E35: 320＜D≤340 | F35: Ⅵ | G35: m | I35: 40 | N35: =H35*I35*M35 -> 0 | O35: 甲级 | Q35: =N35*P35 -> 0 | R35: =N35+Q35 -> 0 | S35: 表3.3-2、表3.3-5 | X35: 6761.3762 | Z35: 1.5 | AB35: =VLOOKUP(O35,{"甲级","1.2";"乙级","1.0";"丙级","0.8"},2,0) -> 1.2 | AD35: =H35+AG35-X35 -> -6761.3762 | AE35: =M35+AH35-Z35 -> -1.5 | AF35: =P35+AI35-AB35 -> -1.2
... A37: 33 | E37: 360＜D≤380 | F37: Ⅵ | G37: m | I37: 30 | N37: =H37*I37*M37 -> 0 | O37: 甲级 | Q37: =N37*P37 -> 0 | R37: =N37+Q37 -> 0 | S37: 表3.3-2、表3.3-5 | X37: 6761.3762 | Z37: 1.5 | AB37: =VLOOKUP(O37,{"甲级","1.2";"乙级","1.0";"丙级","0.8"},2,0) -> 1.2 | AD37: =H37+AG37-X37 -> -6761.3762 | AE37: =M37+AH37-Z37 -> -1.5 | AF37: =P37+AI37-AB37 -> -1.2
A38: 34 | E38: 380＜D≤400 | F38: Ⅵ | G38: m | I38: 10 | N38: =H38*I38*M38 -> 0 | O38: 甲级 | Q38: =N38*P38 -> 0 | R38: =N38+Q38 -> 0 | X38: 6761.3762 | Z38: 1.5 | AB38: =VLOOKUP(O38,{"甲级","1.2";"乙级","1.0";"丙级","0.8"},2,0) -> 1.2 | AD38: =H38+AG38-X38 -> -6761.3762 | AE38: =M38+AH38-Z38 -> -1.5 | AF38: =P38+AI38-AB38 -> -1.2
A39: 35 | E39: 400＜D≤420 | F39: Ⅵ | G39: m | N39: =H39*I39*M39 -> 0 | O39: 甲级 | Q39: =N39*P39 -> 0 | R39: =N39+Q39 -> 0 | X39: 8113.6514 | Z39: 1.5 | AB39: =VLOOKUP(O39,{"甲级","1.2";"乙级","1.0";"丙级","0.8"},2,0) -> 1.2 | AD39: =H39+AG39-X39 -> -8113.6514 | AE39: =M39+AH39-Z39 -> -1.5 | AF39: =P39+AI39-AB39 -> -1.2
A40: 36 | C40: 钻探 | D40: 水域 | E40: D≤10 | F40: Ⅲ | G40: m | I40: 25 | L40: 水深<10m系数2.0，泥浆护壁系数1.5 | N40: =H40*I40*M40 -> 0 | O40: 甲级 | Q40: =N40*P40 -> 0 | R40: =N40+Q40 -> 0 | S40: 表3.3-2、表3.3-5 | T40: 水上作业系数2.5 | X40: =VLOOKUP(F40,{"Ⅰ","46";"Ⅱ","71";"Ⅲ","117";"Ⅳ","207";"Ⅴ","301";"Ⅵ","382"},2,0) -> 117 | Y40: 水上作业系数2.5 | Z40: 2.5 | AB40: =VLOOKUP(O40,{"甲级","1.2";"乙级","1.0";"丙级","0.8"},2,0) -> 1.2 | AD40: =H40+AG40-X40 -> -117 | AE40: =M40+AH40-Z40 -> -2.5 | AF40: =P40+AI40-AB40 -> -1.2
A41: 37 | E41: D≤10 | F41: Ⅳ | G41: m | I41: 25 | L41: 水深<10m系数2.0，泥浆护壁系数1.5 | N41: =H41*I41*M41 -> 0 | O41: 甲级 | Q41: =N41*P41 -> 0 | R41: =N41+Q41 -> 0 | S41: 表3.3-2、表3.3-5 | T41: 水上作业系数2.5 | X41: =VLOOKUP(F41,{"Ⅰ","46";"Ⅱ","71";"Ⅲ","117";"Ⅳ","207";"Ⅴ","301";"Ⅵ","382"},2,0) -> 207 | Y41: 水上作业系数2.5 | Z41: 2.5 | AB41: =VLOOKUP(O41,{"甲级","1.2";"乙级","1.0";"丙级","0.8"},2,0) -> 1.2 | AD41: =H41+AG41-X41 -> -207 | AE41: =M41+AH41-Z41 -> -2.5 | AF41: =P41+AI41-AB41 -> -1.2
A42: 38 | E42: 10＜D≤20 | F42: Ⅳ | G42: m | I42: 50 | N42: =H42*I42*M42 -> 0 | O42: 甲级 | Q42: =N42*P42 -> 0 | R42: =N42+Q42 -> 0 | S42: 表3.3-2、表3.3-5 | X42: =VLOOKUP(F42,{"Ⅰ","58";"Ⅱ","89";"Ⅲ","147";"Ⅳ","259";"Ⅴ","377";"Ⅵ","477"},2,0) -> 259 | Z42: 2.5 | AB42: =VLOOKUP(O42,{"甲级","1.2";"乙级","1.0";"丙级","0.8"},2,0) -> 1.2 | AD42: =H42+AG42-X42 -> -259 | AE42: =M42+AH42-Z42 -> -2.5 | AF42: =P42+AI42-AB42 -> -1.2
A43: 39 | E43: 20＜D≤30 | F43: Ⅳ | G43: m | I43: 50 | N43: =H43*I43*M43 -> 0 | O43: 甲级 | Q43: =N43*P43 -> 0 | R43: =N43+Q43 -> 0 | S43: 表3.3-2、表3.3-5 | X43: =VLOOKUP(F43,{"Ⅰ","69";"Ⅱ","107";"Ⅲ","176";"Ⅳ","311";"Ⅴ","452";"Ⅵ","573"},2,0) -> 311 | Z43: 2.5 | AB43: =VLOOKUP(O43,{"甲级","1.2";"乙级","1.0";"丙级","0.8"},2,0) -> 1.2 | AD43: =H43+AG43-X43 -> -311 | AE43: =M43+AH43-Z43 -> -2.5 | AF43: =P43+AI43-AB43 -> -1.2
A44: 40 | E44: 30＜D≤40 | F44: Ⅳ | G44: m | I44: 25 | N44: =H44*I44*M44 -> 0 | O44: 甲级 | Q44: =N44*P44 -> 0 | R44: =N44+Q44 -> 0 | S44: 表3.3-2、表3.3-5 | X44: =VLOOKUP(F44,{"Ⅰ","82";"Ⅱ","127";"Ⅲ","209";"Ⅳ","368";"Ⅴ","536";"Ⅵ","680"},2,0) -> 368 | Z44: 2.5 | AB44: =VLOOKUP(O44,{"甲级","1.2";"乙级","1.0";"丙级","0.8"},2,0) -> 1.2 | AD44: =H44+AG44-X44 -> -368 | AE44: =M44+AH44-Z44 -> -2.5 | AF44: =P44+AI44-AB44 -> -1.2
A45: 41 | E45: 30＜D≤40 | F45: Ⅴ | G45: m | I45: 25 | N45: =H45*I45*M45 -> 0 | O45: 甲级 | Q45: =N45*P45 -> 0 | R45: =N45+Q45 -> 0 | S45: 表3.3-2、表3.3-5 | X45: =VLOOKUP(F45,{"Ⅰ","82";"Ⅱ","127";"Ⅲ","209";"Ⅳ","368";"Ⅴ","536";"Ⅵ","680"},2,0) -> 536 | Z45: 2.5 | AB45: =VLOOKUP(O45,{"甲级","1.2";"乙级","1.0";"丙级","0.8"},2,0) -> 1.2 | AD45: =H45+AG45-X45 -> -536 | AE45: =M45+AH45-Z45 -> -2.5 | AF45: =P45+AI45-AB45 -> -1.2
A46: 42 | E46: 40＜D≤50 | F46: Ⅴ | G46: m | I46: 25 | N46: =H46*I46*M46 -> 0 | O46: 甲级 | Q46: =N46*P46 -> 0 | R46: =N46+Q46 -> 0 | S46: 表3.3-2、表3.3-5 | X46: =VLOOKUP(F46,{"Ⅰ","98";"Ⅱ","151";"Ⅲ","249";"Ⅳ","439";"Ⅴ","639";"Ⅵ","809"},2,0) -> 639 | Z46: 2.5 | AB46: =VLOOKUP(O46,{"甲级","1.2";"乙级","1.0";"丙级","0.8"},2,0) -> 1.2 | AD46: =H46+AG46-X46 -> -639 | AE46: =M46+AH46-Z46 -> -2.5 | AF46: =P46+AI46-AB46 -> -1.2
A47: 43 | E47: 40＜D≤50 | F47: Ⅵ | G47: m | I47: 25 | N47: =H47*I47*M47 -> 0 | O47: 甲级 | Q47: =N47*P47 -> 0 | R47: =N47+Q47 -> 0 | S47: 表3.3-2、表3.3-5 | X47: =VLOOKUP(F47,{"Ⅰ","98";"Ⅱ","151";"Ⅲ","249";"Ⅳ","439";"Ⅴ","639";"Ⅵ","809"},2,0) -> 809 | Z47: 2.5 | AB47: =VLOOKUP(O47,{"甲级","1.2";"乙级","1.0";"丙级","0.8"},2,0) -> 1.2 | AD47: =H47+AG47-X47 -> -809 | AE47: =M47+AH47-Z47 -> -2.5 | AF47: =P47+AI47-AB47 -> -1.2
A48: 44 | E48: 50＜D≤60 | F48: Ⅵ | G48: m | I48: 50 | N48: =H48*I48*M48 -> 0 | O48: 甲级 | Q48: =N48*P48 -> 0 | R48: =N48+Q48 -> 0 | S48: 表3.3-2、表3.3-5 | X48: =VLOOKUP(F48,{"Ⅰ","109";"Ⅱ","168";"Ⅲ","277";"Ⅳ","489";"Ⅴ","711";"Ⅵ","901"},2,0) -> 901 | Z48: 2.5 | AB48: =VLOOKUP(O48,{"甲级","1.2";"乙级","1.0";"丙级","0.8"},2,0) -> 1.2 | AD48: =H48+AG48-X48 -> -901 | AE48: =M48+AH48-Z48 -> -2.5 | AF48: =P48+AI48-AB48 -> -1.2
A49: 45 | E49: 60＜D≤80 | F49: Ⅵ | G49: m | I49: 35 | N49: =H49*I49*M49 -> 0 | O49: 甲级 | Q49: =N49*P49 -> 0 | R49: =N49+Q49 -> 0 | S49: 表3.3-2、表3.3-5 | X49: =VLOOKUP(F49,{"Ⅰ","121";"Ⅱ","187";"Ⅲ","307";"Ⅳ","542";"Ⅴ","789";"Ⅵ","1000"},2,0) -> 1000 | Z49: 2.5 | AB49: =VLOOKUP(O49,{"甲级","1.2";"乙级","1.0";"丙级","0.8"},2,0) -> 1.2 | AD49: =H49+AG49-X49 -> -1000 | AE49: =M49+AH49-Z49 -> -2.5 | AF49: =P49+AI49-AB49 -> -1.2
A50: 46 | E50: 80＜D≤100 | F50: Ⅵ | G50: m | N50: =H50*I50*M50 -> 0 | O50: 甲级 | Q50: =N50*P50 -> 0 | R50: =N50+Q50 -> 0 | S50: 表3.3-2、表3.3-5 | X50: =VLOOKUP(F50,{"Ⅰ","132";"Ⅱ","204";"Ⅲ","335";"Ⅳ","592";"Ⅴ","862";"Ⅵ","1092"},2,0) -> 1092 | Z50: 2.5 | AB50: =VLOOKUP(O50,{"甲级","1.2";"乙级","1.0";"丙级","0.8"},2,0) -> 1.2 | AD50: =H50+AG50-X50 -> -1092 | AE50: =M50+AH50-Z50 -> -2.5 | AF50: =P50+AI50-AB50 -> -1.2
A51: 47 | E51: 100＜D≤120 | F51: =F50 -> Ⅵ | G51: m | N51: =H51*I51*M51 -> 0 | O51: 甲级 | Q51: =N51*P51 -> 0 | R51: =N51+Q51 -> 0 | S51: 表3.3-2、表3.3-5 | X51: =H50*1.2 -> 0 | Z51: 2.5 | AB51: =VLOOKUP(O51,{"甲级","1.2";"乙级","1.0";"丙级","0.8"},2,0) -> 1.2 | AD51: =H51+AG51-X51 -> 0 | AE51: =M51+AH51-Z51 -> -2.5 | AF51: =P51+AI51-AB51 -> -1.2
A52: 48 | E52: 120＜D≤140 | F52: =F50 -> Ⅵ | G52: m | N52: =H52*I52*M52 -> 0 | O52: 甲级 | Q52: =N52*P52 -> 0 | R52: =N52+Q52 -> 0 | S52: 表3.3-2、表3.3-5 | X52: =H51*1.2 -> 0 | Z52: 2.5 | AB52: =VLOOKUP(O52,{"甲级","1.2";"乙级","1.0";"丙级","0.8"},2,0) -> 1.2 | AD52: =H52+AG52-X52 -> 0 | AE52: =M52+AH52-Z52 -> -2.5 | AF52: =P52+AI52-AB52 -> -1.2
A53: 49 | E53: 140＜D≤160 | F53: =F50 -> Ⅵ | G53: m | N53: =H53*I53*M53 -> 0 | O53: 甲级 | Q53: =N53*P53 -> 0 | R53: =N53+Q53 -> 0 | S53: 表3.3-2、表3.3-5 | X53: =H52*1.2 -> 0 | Z53: 2.5 | AB53: =VLOOKUP(O53,{"甲级","1.2";"乙级","1.0";"丙级","0.8"},2,0) -> 1.2 | AD53: =H53+AG53-X53 -> 0 | AE53: =M53+AH53-Z53 -> -2.5 | AF53: =P53+AI53-AB53 -> -1.2
A54: 50 | E54: 160＜D≤180 | F54: =F50 -> Ⅵ | G54: m | N54: =H54*I54*M54 -> 0 | O54: 甲级 | Q54: =N54*P54 -> 0 | R54: =N54+Q54 -> 0 | S54: 表3.3-2、表3.3-5 | X54: =H53*1.2 -> 0 | Z54: 2.5 | AB54: =VLOOKUP(O54,{"甲级","1.2";"乙级","1.0";"丙级","0.8"},2,0) -> 1.2 | AD54: =H54+AG54-X54 -> 0 | AE54: =M54+AH54-Z54 -> -2.5 | AF54: =P54+AI54-AB54 -> -1.2
A55: 51 | E55: 180＜D≤200 | F55: =F50 -> Ⅵ | G55: m | N55: =H55*I55*M55 -> 0 | O55: 甲级 | Q55: =N55*P55 -> 0 | R55: =N55+Q55 -> 0 | S55: 表3.3-2、表3.3-5 | X55: =H54*1.2 -> 0 | Z55: 2.5 | AB55: =VLOOKUP(O55,{"甲级","1.2";"乙级","1.0";"丙级","0.8"},2,0) -> 1.2 | AD55: =H55+AG55-X55 -> 0 | AE55: =M55+AH55-Z55 -> -2.5 | AF55: =P55+AI55-AB55 -> -1.2
A56: 52 | C56: 探井 | E56: D≤2 | F56: Ⅱ | G56: m | N56: =H56*I56*M56 -> 0 | O56: 甲级 | Q56: =N56*P56 -> 0 | R56: =N56+Q56 -> 0 | S56: 表3.3-2、表3.3-5 | X56: =VLOOKUP(F56,{"Ⅰ","50";"Ⅱ","63";"Ⅲ","78";"Ⅳ","125";"Ⅴ","200";"Ⅵ","250"},2,0) -> 63 | Z56: 1.3 | AB56: =VLOOKUP(O56,{"甲级","1.2";"乙级","1.0";"丙级","0.8"},2,0) -> 1.2 | AD56: =H56+AG56-X56 -> -63 | AE56: =M56+AH56-Z56 -> -1.3 | AF56: =P56+AI56-AB56 -> -1.2
A57: 53 | E57: 2＜D≤5 | F57: Ⅲ | G57: m | N57: =H57*I57*M57 -> 0 | O57: 甲级 | Q57: =N57*P57 -> 0 | R57: =N57+Q57 -> 0 | S57: 表3.3-2、表3.3-5 | X57: =VLOOKUP(F57,{"Ⅰ","63";"Ⅱ","78";"Ⅲ","97";"Ⅳ","156";"Ⅴ","250";"Ⅵ","313"},2,0) -> 97 | Z57: 1.3 | AB57: =VLOOKUP(O57,{"甲级","1.2";"乙级","1.0";"丙级","0.8"},2,0) -> 1.2 | AD57: =H57+AG57-X57 -> -97 | AE57: =M57+AH57-Z57 -> -1.3 | AF57: =P57+AI57-AB57 -> -1.2
A58: 54 | E58: 5＜D≤10 | F58: Ⅰ | G58: m | N58: =H58*I58*M58 -> 0 | O58: 甲级 | Q58: =N58*P58 -> 0 | R58: =N58+Q58 -> 0 | S58: 表3.3-2、表3.3-5 | X58: =VLOOKUP(F58,{"Ⅰ","78";"Ⅱ","97";"Ⅲ","120";"Ⅳ","194";"Ⅴ","310";"Ⅵ","388"},2,0) -> 78 | Z58: 1.3 | AB58: =VLOOKUP(O58,{"甲级","1.2";"乙级","1.0";"丙级","0.8"},2,0) -> 1.2 | AD58: =H58+AG58-X58 -> -78 | AE58: =M58+AH58-Z58 -> -1.3 | AF58: =P58+AI58-AB58 -> -1.2
A59: 55 | E59: 10＜D≤20 | F59: Ⅰ | G59: m | N59: =H59*I59*M59 -> 0 | O59: 甲级 | Q59: =N59*P59 -> 0 | R59: =N59+Q59 -> 0 | S59: 表3.3-2、表3.3-5 | X59: =VLOOKUP(F59,{"Ⅰ","103";"Ⅱ","128";"Ⅲ","159";"Ⅳ","256";"Ⅴ","410";"Ⅵ","513"},2,0) -> 103 | Z59: 1.3 | AB59: =VLOOKUP(O59,{"甲级","1.2";"乙级","1.0";"丙级","0.8"},2,0) -> 1.2 | AD59: =H59+AG59-X59 -> -103 | AE59: =M59+AH59-Z59 -> -1.3 | AF59: =P59+AI59-AB59 -> -1.2
A60: 56 | C60: 探槽 | E60: D≤2 | F60: Ⅲ | G60: m3 | I60: 18.02167 | N60: =H60*I60*M60 -> 0 | O60: 甲级 | Q60: =N60*P60 -> 0 | R60: =N60+Q60 -> 0 | S60: 表3.3-2、表3.3-5 | X60: =VLOOKUP(F60,{"Ⅰ","40";"Ⅱ","52";"Ⅲ","72";"Ⅳ","92";"Ⅴ","120";"Ⅵ","148"},2,0) -> 72 | Z60: 1 | AB60: =VLOOKUP(O60,{"甲级","1.2";"乙级","1.0";"丙级","0.8"},2,0) -> 1.2 | AD60: =H60+AG60-X60 -> -72 | AE60: =M60+AH60-Z60 -> -1 | AF60: =P60+AI60-AB60 -> -1.2
A61: 57 | E61: D＞2 | F61: Ⅰ | G61: m3 | N61: =H61*I61*M61 -> 0 | O61: 甲级 | Q61: =N61*P61 -> 0 | R61: =N61+Q61 -> 0 | S61: 表3.3-2、表3.3-5 | X61: =VLOOKUP(F61,{"Ⅰ","58";"Ⅱ","75";"Ⅲ","104";"Ⅳ","133";"Ⅴ","174";"Ⅵ","215"},2,0) -> 58 | Z61: 1.3 | AB61: =VLOOKUP(O61,{"甲级","1.2";"乙级","1.0";"丙级","0.8"},2,0) -> 1.2 | AD61: =H61+AG61-X61 -> -58 | AE61: =M61+AH61-Z61 -> -1.3 | AF61: =P61+AI61-AB61 -> -1.2
A62: 58 | C62: 取样 | E62: 钻孔取土样 | F62: ≤30m | G62: 件 | I62: 48 | N62: =H62*I62*M62 -> 0 | O62: 甲级 | Q62: =N62*P62 -> 0 | R62: =N62+Q62 -> 0 | S62: 表3.3-3、表3.3-5 | X62: =IF(F62="≤30m",65,95) -> 65 | Z62: 1 | AB62: =VLOOKUP(O62,{"甲级","1.2";"乙级","1.0";"丙级","0.8"},2,0) -> 1.2 | AD62: =H62+AG62-X62 -> -65 | AE62: =M62+AH62-Z62 -> -1 | AF62: =P62+AI62-AB62 -> -1.2
A63: 59 | E63: 探井取土样 | F63: ≤30m | G63: 件 | I63: 18 | N63: =H63*I63*M63 -> 0 | O63: 甲级 | Q63: =N63*P63 -> 0 | R63: =N63+Q63 -> 0 | S63: 表3.3-3、表3.3-5 | X63: =IF(F63="≤30m",100,150) -> 100 | Z63: 1 | AB63: =VLOOKUP(O63,{"甲级","1.2";"乙级","1.0";"丙级","0.8"},2,0) -> 1.2 | AD63: =H63+AG63-X63 -> -100 | AE63: =M63+AH63-Z63 -> -1 | AF63: =P63+AI63-AB63 -> -1.2
A64: 60 | E64: 取扰动样 | G64: 件 | I64: 40 | N64: =H64*I64*M64 -> 0 | O64: 甲级 | Q64: =N64*P64 -> 0 | R64: =N64+Q64 -> 0 | S64: 表3.3-3、表3.3-5 | X64: 15 | Z64: 1 | AB64: =VLOOKUP(O64,{"甲级","1.2";"乙级","1.0";"丙级","0.8"},2,0) -> 1.2 | AD64: =H64+AG64-X64 -> -15 | AE64: =M64+AH64-Z64 -> -1 | AF64: =P64+AI64-AB64 -> -1.2
A65: 61 | E65: 岩芯取石样 | G65: 件 | I65: 202 | N65: =H65*I65*M65 -> 0 | O65: 甲级 | Q65: =N65*P65 -> 0 | R65: =N65+Q65 -> 0 | S65: 表3.3-3、表3.3-5 | X65: 25 | Z65: 1 | AB65: =VLOOKUP(O65,{"甲级","1.2";"乙级","1.0";"丙级","0.8"},2,0) -> 1.2 | AD65: =H65+AG65-X65 -> -25 | AE65: =M65+AH65-Z65 -> -1 | AF65: =P65+AI65-AB65 -> -1.2
A66: 62 | E66: 水样 | G66: 件 | I66: 7 | N66: =H66*I66*M66 -> 0 | O66: 甲级 | Q66: =N66*P66 -> 0 | R66: =N66+Q66 -> 0 | S66: 表3.3-3、表3.3-5 | X66: 40 | Z66: 1 | AB66: =VLOOKUP(O66,{"甲级","1.2";"乙级","1.0";"丙级","0.8"},2,0) -> 1.2 | AD66: =H66+AG66-X66 -> -40 | AE66: =M66+AH66-Z66 -> -1 | AF66: =P66+AI66-AB66 -> -1.2
A67: 63 | C67: 标准贯入试验 | E67: D≤20 | F67: Ⅲ | G67: 次 | I67: 48 | N67: =H67*I67*M67 -> 0 | O67: 甲级 | Q67: =N67*P67 -> 0 | R67: =N67+Q67 -> 0 | S67: 表3.3-4、表3.3-5 | X67: =VLOOKUP(F67,{"Ⅰ","80";"Ⅱ","108";"Ⅲ","144"},2,0) -> 144 | Z67: 1 | AB67: =VLOOKUP(O67,{"甲级","1.2";"乙级","1.0";"丙级","0.8"},2,0) -> 1.2 | AD67: =H67+AG67-X67 -> -144 | AE67: =M67+AH67-Z67 -> -1 | AF67: =P67+AI67-AB67 -> -1.2
A68: 64 | E68: 20＜D≤50 | F68: Ⅲ | G68: 次 | I68: 24 | N68: =H68*I68*M68 -> 0 | O68: 甲级 | Q68: =N68*P68 -> 0 | R68: =N68+Q68 -> 0 | S68: 表3.3-4、表3.3-5 | X68: =VLOOKUP(F68,{"Ⅰ","120";"Ⅱ","162";"Ⅲ","216"},2,0) -> 216 | Z68: 1 | AB68: =VLOOKUP(O68,{"甲级","1.2";"乙级","1.0";"丙级","0.8"},2,0) -> 1.2 | AD68: =H68+AG68-X68 -> -216 | AE68: =M68+AH68-Z68 -> -1 | AF68: =P68+AI68-AB68 -> -1.2
A69: 65 | E69: D＞50 | F69: Ⅰ | G69: 次 | N69: =H69*I69*M69 -> 0 | O69: 甲级 | Q69: =N69*P69 -> 0 | R69: =N69+Q69 -> 0 | S69: 表3.3-4、表3.3-5 | X69: =VLOOKUP(F69,{"Ⅰ","144";"Ⅱ","194";"Ⅲ","259"},2,0) -> 144 | Z69: 1.3 | AB69: =VLOOKUP(O69,{"甲级","1.2";"乙级","1.0";"丙级","0.8"},2,0) -> 1.2 | AD69: =H69+AG69-X69 -> -144 | AE69: =M69+AH69-Z69 -> -1.3 | AF69: =P69+AI69-AB69 -> -1.2
A70: 66 | C70: 动力触探 | D70: 重型 | E70: D≤10 | F70: Ⅲ | G70: m | I70: 13 | N70: =H70*I70*M70 -> 0 | O70: 甲级 | Q70: =N70*P70 -> 0 | R70: =N70+Q70 -> 0 | S70: 表3.3-4、表3.3-5 | X70: =VLOOKUP(F70,{"Ⅰ","50";"Ⅱ","78";"Ⅲ","128";"Ⅳ","300";"Ⅴ","375";"Ⅵ","425"},2,0) -> 128 | Z70: 1 | AB70: =VLOOKUP(O70,{"甲级","1.2";"乙级","1.0";"丙级","0.8"},2,0) -> 1.2 | AD70: =H70+AG70-X70 -> -128 | AE70: =M70+AH70-Z70 -> -1 | AF70: =P70+AI70-AB70 -> -1.2
A71: 67 | E71: D≤10 | F71: Ⅲ | G71: m | I71: 4 | N71: =H71*I71*M71 -> 0 | O71: 甲级 | Q71: =N71*P71 -> 0 | R71: =N71+Q71 -> 0 | S71: 表3.3-4、表3.3-5 | X71: =VLOOKUP(F71,{"Ⅰ","50";"Ⅱ","78";"Ⅲ","128";"Ⅳ","300";"Ⅴ","375";"Ⅵ","425"},2,0) -> 128 | Z71: 1 | AB71: =VLOOKUP(O71,{"甲级","1.2";"乙级","1.0";"丙级","0.8"},2,0) -> 1.2 | AD71: =H71+AG71-X71 -> -128 | AE71: =M71+AH71-Z71 -> -1 | AF71: =P71+AI71-AB71 -> -1.2
A72: 68 | E72: D≤10 | F72: Ⅳ | G72: m | N72: =H72*I72*M72 -> 0 | O72: 甲级 | Q72: =N72*P72 -> 0 | R72: =N72+Q72 -> 0 | S72: 表3.3-4、表3.3-5 | X72: =VLOOKUP(F72,{"Ⅰ","50";"Ⅱ","78";"Ⅲ","128";"Ⅳ","300";"Ⅴ","375";"Ⅵ","425"},2,0) -> 300 | Z72: 1.3 | AB72: =VLOOKUP(O72,{"甲级","1.2";"乙级","1.0";"丙级","0.8"},2,0) -> 1.2 | AD72: =H72+AG72-X72 -> -300 | AE72: =M72+AH72-Z72 -> -1.3 | AF72: =P72+AI72-AB72 -> -1.2
A73: 69 | E73: 10＜D≤20 | F73: Ⅳ | G73: m | N73: =H73*I73*M73 -> 0 | O73: 甲级 | Q73: =N73*P73 -> 0 | R73: =N73+Q73 -> 0 | S73: 表3.3-4、表3.3-5 | X73: =VLOOKUP(F73,{"Ⅰ","63";"Ⅱ","97";"Ⅲ","159";"Ⅳ","375";"Ⅴ","469";"Ⅵ","531"},2,0) -> 375 | Z73: 1.3 | AB73: =VLOOKUP(O73,{"甲级","1.2";"乙级","1.0";"丙级","0.8"},2,0) -> 1.2 | AD73: =H73+AG73-X73 -> -375 | AE73: =M73+AH73-Z73 -> -1.3 | AF73: =P73+AI73-AB73 -> -1.2
A74: 70 | E74: 10＜D≤20 | F74: Ⅳ | G74: m | N74: =H74*I74*M74 -> 0 | O74: 甲级 | Q74: =N74*P74 -> 0 | R74: =N74+Q74 -> 0 | S74: 表3.3-4、表3.3-5 | X74: =VLOOKUP(F74,{"Ⅰ","63";"Ⅱ","97";"Ⅲ","159";"Ⅳ","375";"Ⅴ","469";"Ⅵ","531"},2,0) -> 375 | Z74: 1.3 | AB74: =VLOOKUP(O74,{"甲级","1.2";"乙级","1.0";"丙级","0.8"},2,0) -> 1.2 | AD74: =H74+AG74-X74 -> -375 | AE74: =M74+AH74-Z74 -> -1.3 | AF74: =P74+AI74-AB74 -> -1.2
A75: 71 | E75: 20＜D≤30 | F75: Ⅰ | G75: m | N75: =H75*I75*M75 -> 0 | O75: 甲级 | Q75: =N75*P75 -> 0 | R75: =N75+Q75 -> 0 | S75: 表3.3-4、表3.3-5 | X75: =VLOOKUP(F75,{"Ⅰ","75";"Ⅱ","116";"Ⅲ","191";"Ⅳ","450";"Ⅴ","563";"Ⅵ","638"},2,0) -> 75 | Z75: 1.3 | AB75: =VLOOKUP(O75,{"甲级","1.2";"乙级","1.0";"丙级","0.8"},2,0) -> 1.2 | AD75: =H75+AG75-X75 -> -75 | AE75: =M75+AH75-Z75 -> -1.3 | AF75: =P75+AI75-AB75 -> -1.2
A76: 72 | E76: 30＜D≤40 | F76: Ⅰ | G76: m | N76: =H76*I76*M76 -> 0 | O76: 甲级 | Q76: =N76*P76 -> 0 | R76: =N76+Q76 -> 0 | S76: 表3.3-4、表3.3-5 | X76: =VLOOKUP(F76,{"Ⅰ","89";"Ⅱ","138";"Ⅲ","227";"Ⅳ","534";"Ⅴ","668";"Ⅵ","757"},2,0) -> 89 | Z76: 1.3 | AB76: =VLOOKUP(O76,{"甲级","1.2";"乙级","1.0";"丙级","0.8"},2,0) -> 1.2 | AD76: =H76+AG76-X76 -> -89 | AE76: =M76+AH76-Z76 -> -1.3 | AF76: =P76+AI76-AB76 -> -1.2
A77: 73 | E77: 40＜D≤50 | F77: Ⅰ | G77: m | N77: =H77*I77*M77 -> 0 | O77: 甲级 | Q77: =N77*P77 -> 0 | R77: =N77+Q77 -> 0 | S77: 表3.3-4、表3.3-5 | X77: =VLOOKUP(F77,{"Ⅰ","106";"Ⅱ","164";"Ⅲ","270";"Ⅳ","636";"Ⅴ","795";"Ⅵ","901"},2,0) -> 106 | Z77: 1.3 | AB77: =VLOOKUP(O77,{"甲级","1.2";"乙级","1.0";"丙级","0.8"},2,0) -> 1.2 | AD77: =H77+AG77-X77 -> -106 | AE77: =M77+AH77-Z77 -> -1.3 | AF77: =P77+AI77-AB77 -> -1.2
A78: 74 | C78: 静力触探 | D78: 双桥 | E78: D≤10 | F78: Ⅰ | G78: m | N78: =H78*I78*M78 -> 0 | O78: 甲级 | Q78: =N78*P78 -> 0 | R78: =N78+Q78 -> 0 | S78: 表3.3-4、表3.3-5 | X78: =VLOOKUP(F78,{"Ⅰ","39.10";"Ⅱ","56.35";"Ⅲ","94.30"},2,0) -> 39.10 | Z78: 1.3 | AB78: =VLOOKUP(O78,{"甲级","1.2";"乙级","1.0";"丙级","0.8"},2,0) -> 1.2 | AD78: =H78+AG78-X78 -> -39.1 | AE78: =M78+AH78-Z78 -> -1.3 | AF78: =P78+AI78-AB78 -> -1.2
A79: 75 | E79: 10＜D≤20 | F79: Ⅰ | G79: m | N79: =H79*I79*M79 -> 0 | O79: 甲级 | Q79: =N79*P79 -> 0 | R79: =N79+Q79 -> 0 | S79: 表3.3-4、表3.3-5 | X79: =VLOOKUP(F79,{"Ⅰ","49.45";"Ⅱ","71.30";"Ⅲ","117.30"},2,0) -> 49.45 | Z79: 1.3 | AB79: =VLOOKUP(O79,{"甲级","1.2";"乙级","1.0";"丙级","0.8"},2,0) -> 1.2 | AD79: =H79+AG79-X79 -> -49.45 | AE79: =M79+AH79-Z79 -> -1.3 | AF79: =P79+AI79-AB79 -> -1.2
A80: 76 | E80: 20＜D≤30 | F80: Ⅰ | G80: m | N80: =H80*I80*M80 -> 0 | O80: 甲级 | Q80: =N80*P80 -> 0 | R80: =N80+Q80 -> 0 | S80: 表3.3-4、表3.3-5 | X80: =VLOOKUP(F80,{"Ⅰ","58.65";"Ⅱ","85.10";"Ⅲ","140.30"},2,0) -> 58.65 | Z80: 1.3 | AB80: =VLOOKUP(O80,{"甲级","1.2";"乙级","1.0";"丙级","0.8"},2,0) -> 1.2 | AD80: =H80+AG80-X80 -> -58.65 | AE80: =M80+AH80-Z80 -> -1.3 | AF80: =P80+AI80-AB80 -> -1.2
A81: 77 | E81: 30＜D≤40 | F81: Ⅰ | G81: m | N81: =H81*I81*M81 -> 0 | O81: 甲级 | Q81: =N81*P81 -> 0 | R81: =N81+Q81 -> 0 | S81: 表3.3-4、表3.3-5 | X81: =VLOOKUP(F81,{"Ⅰ","70.15";"Ⅱ","101.20";"Ⅲ","166.75"},2,0) -> 70.15 | Z81: 1.3 | AB81: =VLOOKUP(O81,{"甲级","1.2";"乙级","1.0";"丙级","0.8"},2,0) -> 1.2 | AD81: =H81+AG81-X81 -> -70.15 | AE81: =M81+AH81-Z81 -> -1.3 | AF81: =P81+AI81-AB81 -> -1.2
A82: 78 | E82: 40＜D≤50 | F82: Ⅰ | G82: m | N82: =H82*I82*M82 -> 0 | O82: 甲级 | Q82: =N82*P82 -> 0 | R82: =N82+Q82 -> 0 | S82: 表3.3-4、表3.3-5 | X82: =VLOOKUP(F82,{"Ⅰ","82.80";"Ⅱ","120.75";"Ⅲ","198.95"},2,0) -> 82.80 | Z82: 1.3 | AB82: =VLOOKUP(O82,{"甲级","1.2";"乙级","1.0";"丙级","0.8"},2,0) -> 1.2 | AD82: =H82+AG82-X82 -> -82.8 | AE82: =M82+AH82-Z82 -> -1.3 | AF82: =P82+AI82-AB82 -> -1.2
A83: 79 | E83: 50＜D≤60 | F83: Ⅰ | G83: m | N83: =H83*I83*M83 -> 0 | O83: 甲级 | Q83: =N83*P83 -> 0 | R83: =N83+Q83 -> 0 | S83: 表3.3-4、表3.3-5 | X83: =VLOOKUP(F83,{"Ⅰ","92";"Ⅱ","133.40";"Ⅲ","221.95"},2,0) -> 92 | Z83: 1.3 | AB83: =VLOOKUP(O83,{"甲级","1.2";"乙级","1.0";"丙级","0.8"},2,0) -> 1.2 | AD83: =H83+AG83-X83 -> -92 | AE83: =M83+AH83-Z83 -> -1.3 | AF83: =P83+AI83-AB83 -> -1.2
A84: 80 | E84: 60＜D≤80 | F84: Ⅰ | G84: m | N84: =H84*I84*M84 -> 0 | O84: 甲级 | Q84: =N84*P84 -> 0 | R84: =N84+Q84 -> 0 | S84: 表3.3-4、表3.3-5 | X84: =VLOOKUP(F84,{"Ⅰ","102.35";"Ⅱ","148.35";"Ⅲ","246.10"},2,0) -> 102.35 | Z84: 1.3 | AB84: =VLOOKUP(O84,{"甲级","1.2";"乙级","1.0";"丙级","0.8"},2,0) -> 1.2 | AD84: =H84+AG84-X84 -> -102.35 | AE84: =M84+AH84-Z84 -> -1.3 | AF84: =P84+AI84-AB84 -> -1.2
A85: 81 | C85: 地应力测试 | D85: 压水致裂 | E85: 孔壁应变法 | G85: 孔 | I85: 3 | N85: =H85*I85*M85 -> 0 | O85: 甲级 | Q85: =N85*P85 -> 0 | R85: =N85+Q85 -> 0 | S85: 表3.3-4、表3.3-5 | X85: 35100 | Z85: 1 | AB85: =VLOOKUP(O85,{"甲级","1.2";"乙级","1.0";"丙级","0.8"},2,0) -> 1.2 | AD85: =H85+AG85-X85 -> -35100 | AE85: =M85+AH85-Z85 -> -1 | AF85: =P85+AI85-AB85 -> -1.2
A86: 82 | B86: 水文地质勘察 | C86: 压注水试验 | D86: 压水 | E86: D≤20 | G86: 段次 | I86: 70 | N86: =H86*I86*M86 -> 0 | O86: 甲级 | Q86: =N86*P86 -> 0 | R86: =N86+Q86 -> 0 | S86: 表3.3-4、表3.3-5 | X86: 1753 | Z86: 1 | AB86: =VLOOKUP(O86,{"甲级","1.2";"乙级","1.0";"丙级","0.8"},2,0) -> 1.2 | AD86: =H86+AG86-X86 -> -1753 | AE86: =M86+AH86-Z86 -> -1 | AF86: =P86+AI86-AB86 -> -1.2
A87: 83 | E87: D＞20 | G87: 段次 | N87: =H87*I87*M87 -> 0 | O87: 甲级 | Q87: =N87*P87 -> 0 | R87: =N87+Q87 -> 0 | S87: 表3.3-4、表3.3-5 | X87: 2104 | Z87: 1.3 | AB87: =VLOOKUP(O87,{"甲级","1.2";"乙级","1.0";"丙级","0.8"},2,0) -> 1.2 | AD87: =H87+AG87-X87 -> -2104 | AE87: =M87+AH87-Z87 -> -1.3 | AF87: =P87+AI87-AB87 -> -1.2
A88: 84 | D88: 注水 | E88: 钻孔注水 | G88: 段次 | N88: =H88*I88*M88 -> 0 | O88: 甲级 | Q88: =N88*P88 -> 0 | R88: =N88+Q88 -> 0 | S88: 表3.3-4、表3.3-5 | X88: 409 | Z88: 1.3 | AB88: =VLOOKUP(O88,{"甲级","1.2";"乙级","1.0";"丙级","0.8"},2,0) -> 1.2 | AD88: =H88+AG88-X88 -> -409 | AE88: =M88+AH88-Z88 -> -1.3 | AF88: =P88+AI88-AB88 -> -1.2
A89: 85 | E89: 探井注水 | G89: 段次 | N89: =H89*I89*M89 -> 0 | O89: 甲级 | Q89: =N89*P89 -> 0 | R89: =N89+Q89 -> 0 | S89: 表3.3-4、表3.3-5 | X89: 205 | Z89: 1.3 | AB89: =VLOOKUP(O89,{"甲级","1.2";"乙级","1.0";"丙级","0.8"},2,0) -> 1.2 | AD89: =H89+AG89-X89 -> -205 | AE89: =M89+AH89-Z89 -> -1.3 | AF89: =P89+AI89-AB89 -> -1.2
A90: 86 | C90: 抽水试验 | E90: 利用钻孔抽水 | G90: 台班 | N90: =H90*I90*M90 -> 0 | O90: 复杂 | Q90: =N90*P90 -> 0 | R90: =N90+Q90 -> 0 | S90: 表5.5-1 | X90: 840 | Z90: 1 | AB90: =VLOOKUP(O90,{"简单","0.27";"中等","0.30";"复杂","0.33"},2,0) -> 0.33 | AC90: 【第一层】【系数】要素1：水文地质勘察。 系数："简单","0.27";"中等","0.30";"复杂","0.33" | AD90: =H90+AG90-X90 -> -840 | AE90: =M90+AH90-Z90 -> -1 | AF90: =P90+AI90-AB90 -> -0.33
A91: 87 | C91: 地下水位（温）观测 | D91: 试验观测孔 | G91: 台班 | I91: 32 | N91: =H91*I91*M91 -> 0 | O91: 复杂 | Q91: =N91*P91 -> 0 | R91: =N91+Q91 -> 0 | S91: 表5.5-1 | X91: 170 | Z91: 1 | AB91: =VLOOKUP(O91,{"简单","0.27";"中等","0.30";"复杂","0.33"},2,0) -> 0.33 | AD91: =H91+AG91-X91 -> -170 | AE91: =M91+AH91-Z91 -> -1 | AF91: =P91+AI91-AB91 -> -0.33
A92: 88 | D92: 动态观测距离L（km） | E92: L≤5 | G92: 次 | N92: =H92*I92*M92 -> 0 | O92: 复杂 | Q92: =N92*P92 -> 0 | R92: =N92+Q92 -> 0 | S92: 表5.5-1 | X92: 20 | Z92: 1 | AB92: =VLOOKUP(O92,{"简单","0.27";"中等","0.30";"复杂","0.33"},2,0) -> 0.33 | AD92: =H92+AG92-X92 -> -20 | AE92: =M92+AH92-Z92 -> -1 | AF92: =P92+AI92-AB92 -> -0.33
A93: 89 | E93: 5＜L≤10 | G93: 次 | N93: =H93*I93*M93 -> 0 | O93: 复杂 | Q93: =N93*P93 -> 0 | R93: =N93+Q93 -> 0 | S93: 表5.5-1 | X93: 40 | Z93: 1 | AB93: =VLOOKUP(O93,{"简单","0.27";"中等","0.30";"复杂","0.33"},2,0) -> 0.33 | AD93: =H93+AG93-X93 -> -40 | AE93: =M93+AH93-Z93 -> -1 | AF93: =P93+AI93-AB93 -> -0.33
A94: 90 | E94: L＞10 | G94: 次 | N94: =H94*I94*M94 -> 0 | O94: 复杂 | Q94: =N94*P94 -> 0 | R94: =N94+Q94 -> 0 | S94: 表5.5-1 | X94: 50 | Z94: 1 | AB94: =VLOOKUP(O94,{"简单","0.27";"中等","0.30";"复杂","0.33"},2,0) -> 0.33 | AD94: =H94+AG94-X94 -> -50 | AE94: =M94+AH94-Z94 -> -1 | AF94: =P94+AI94-AB94 -> -0.33
A95: 91 | B95: 工程水文 | C95: 设计洪水 | D95: 设计洪水位 | E95: 河流设计洪水 | F95: 中等 | G95: 设计断面 | N95: =H95*I95*M95 -> 0 | O95: 水文气象 | Q95: =N95*P95 -> 0 | R95: =N95+Q95 -> 0 | S95: 表6.2-2 | X95: =VLOOKUP(F95,{"简单","54600";"中等","78100";"复杂","109300"},2,0) -> 78100 | Z95: 1 | AB95: 0.22 | AC95: 【第一层】【系数】要素1：工程水文。 系数：固定0.22 | AD95: =H95+AG95-X95 -> -78100 | AE95: =M95+AH95-Z95 -> -1 | AF95: =P95+AI95-AB95 -> -0.22
A96: 92 | E96: 小流域暴雨洪水 | F96: 中等 | G96: 设计断面 | I96: 1 | N96: =H96*I96*M96 -> 0 | O96: 水文气象 | Q96: =N96*P96 -> 0 | R96: =N96+Q96 -> 0 | S96: 表6.2-2 | X96: =VLOOKUP(F96,{"简单","6900";"中等","9900";"复杂","13900"},2,0) -> 9900 | Z96: 1 | AB96: 0.22 | AD96: =H96+AG96-X96 -> -9900 | AE96: =M96+AH96-Z96 -> -1 | AF96: =P96+AI96-AB96 -> -0.22
A97: 93 | C97: 河流冲刷 | D97: 工程泥沙 | E97: 河床冲刷 | F97: 中等 | G97: 工程点 | I97: 1 | N97: =H97*I97*M97 -> 0 | O97: 水文气象 | Q97: =N97*P97 -> 0 | R97: =N97+Q97 -> 0 | S97: 表6.2-2 | X97: =VLOOKUP(F97,{"简单","12400";"中等","17800";"复杂","24800"},2,0) -> 17800 | Z97: 1 | AB97: 0.22 | AD97: =H97+AG97-X97 -> -17800 | AE97: =M97+AH97-Z97 -> -1 | AF97: =P97+AI97-AB97 -> -0.22
A98: 94 | B98: 工程物探 | C98: 浅层地震反射或折射 | D98: 敲击 | G98: 检波点·炮 | I98: 2728 | N98: =H98*I98*M98 -> 0 | O98: 物探 | Q98: =N98*P98 -> 0 | R98: =N98+Q98 -> 0 | S98: 表7.2-1 | T98: 山岭隧道地形系数1.7 | X98: 18 | Z98: 1.7 | AB98: =VLOOKUP(O98,{"甲级","1.2";"乙级","1";"丙级","0.8";"物探","0.22"},2,0) -> 0.22 | AC98: 【第一层】【系数】要素1：工程物探。 系数："甲级","1.2";"乙级","1";"丙级","0.8";"物探","0.22" | AD98: =H98+AG98-X98 -> -18 | AE98: =M98+AH98-Z98 -> -1.7 | AF98: =P98+AI98-AB98 -> -0.22
A99: 95 | D99: 爆炸 | E99: 陆地 | G99: 检波点·炮 | N99: =H99*I99*M99 -> 0 | O99: 物探 | Q99: =N99*P99 -> 0 | R99: =N99+Q99 -> 0 | S99: 表7.2-1 | X99: 25 | Z99: 1 | AB99: =VLOOKUP(O99,{"甲级","1.2";"乙级","1";"丙级","0.8";"物探","0.22"},2,0) -> 0.22 | AD99: =H99+AG99-X99 -> -25 | AE99: =M99+AH99-Z99 -> -1 | AF99: =P99+AI99-AB99 -> -0.22
A100: 96 | E100: 水面布点 | F100: 顺流 | G100: 检波点·炮 | N100: =H100*I100*M100 -> 0 | O100: 物探 | Q100: =N100*P100 -> 0 | R100: =N100+Q100 -> 0 | S100: 表7.2-1 | X100: 45 | Z100: 1 | AB100: =VLOOKUP(O100,{"甲级","1.2";"乙级","1";"丙级","0.8";"物探","0.22"},2,0) -> 0.22 | AD100: =H100+AG100-X100 -> -45 | AE100: =M100+AH100-Z100 -> -1 | AF100: =P100+AI100-AB100 -> -0.22
A101: 97 | F101: 横穿 | G101: 检波点·炮 | N101: =H101*I101*M101 -> 0 | O101: 物探 | Q101: =N101*P101 -> 0 | R101: =N101+Q101 -> 0 | S101: 表7.2-1 | X101: 220 | Z101: 1 | AB101: =VLOOKUP(O101,{"甲级","1.2";"乙级","1";"丙级","0.8";"物探","0.22"},2,0) -> 0.22 | AD101: =H101+AG101-X101 -> -220 | AE101: =M101+AH101-Z101 -> -1 | AF101: =P101+AI101-AB101 -> -0.22
...

Sheet 表5-其他费用
A1: 附表5工程勘察其他费用测算表
A2: 序号 | B2: 工作任务 | H2: 实物工作费（元） | O2: 技术工作费（元） | R2: 金额合计
B3: 项目 | D3: 内容 | E3: 类别 | F3: 级别 | G3: 单位 | H3: 基价（元） | I3: 工程量合计 | M3: 附加调整系数 | N3: 小计 | O3: 类别 | P3: 调整系数 | Q3: 小计 | R3: （元） | T3: 标段一 | U3: 标段二
A4: 1 | C4: 办理工程勘察相关许可 | G4: 处 | H4: 2000 | I4: 1 | N4: =I4*H4 -> 2000 | R4: =N4+Q4 -> 2000
A5: 2 | C5: 通航巡护（长江） | G5: 项 | H5: 200000 | I5: 1 | N5: =I5*H5 -> 200000 | R5: =N5+Q5 -> 200000
A6: 3 | C6: 购买资料费 | G6: 项 | H6: 1000 | I6: 3 | N6: =I6*H6 -> 3000 | R6: =N6+Q6 -> 3000
A7: 4 | C7: 水文资料搜集费 | G7: 项 | H7: 10000 | N7: =I7*H7 -> 0 | R7: =N7+Q7 -> 0
A8: 5 | C8: 拆除障碍物，开挖以及修复地下管线 | G8: 孔 | N8: =I8*H8 -> 0 | R8: =N8+Q8 -> 0
A9: 6 | C9: 修通至作业现场道路，接通电源、水源以及平整场地 | G9: 孔 | H9: 2000 | I9: 18 | N9: =I9*H9 -> 36000 | R9: =N9+Q9 -> 36000
A10: 7 | C10: 勘察材料以及加工、封孔费 | G10: 孔 | H10: 500 | I10: 23 | N10: =I10*H10 -> 11500 | R10: =N10+Q10 -> 11500
A11: 8 | C11: 水上作业用船、排、平台以及水监 | G11: 孔 | H11: 10000 | I11: 5 | N11: =I11*H11 -> 50000 | R11: =N11+Q11 -> 50000
A12: 9 | C12: 钻机搬运费 | G12: 孔 | H12: 1000 | I12: 23 | N12: =I12*H12 -> 23000 | R12: =N12+Q12 -> 23000
A13: 10 | C13: 勘察作业大型机具搬运（隧道） | G13: 处 | H13: 10000 | I13: 2 | N13: =I13*H13 -> 20000 | R13: =N13+Q13 -> 20000
A14: 11 | C14: 青苗、树木以及水域养殖物赔偿等 | G14: 孔 | H14: 1500 | I14: 18 | N14: =I14*H14 -> 27000 | R14: =N14+Q14 -> 27000
A15: 12 | C15: 样品包装及运输费 | G15: 件 | H15: 10 | I15: 106 | N15: =I15*H15 -> 1060 | R15: =N15+Q15 -> 1060
A16: 13 | C16: 一级林地报批报告 | G16: 处 | H16: 10000 | I16: 2 | N16: =I16*H16 -> 20000 | R16: =N16+Q16 -> 20000
A17: 合计 | N17: =SUM(N4:N16) -> 393560 | Q17: =SUM(Q4:Q14) -> 0 | R17: =SUM(R4:R16) -> 393560
